{"item":{"id":"item_65108","displayName":"树液","price":5,"sellPrice":1,"sellAt":[],"stackable":true,"inventoryCategory":"Resource","displayKey":"Resource","description":"取自树木的粘性物质。","qualities":{},"iconName":"Sap_Sprite","tags":["income.other"]},"fromEnemies":[{"key":"slimeV2","displayName":"基础粘液怪","description":null,"experience":10,"iconName":"Slime_Sprite","image":"Slime_2880x2160","dropRates":[{"item":{"id":"item_65108","displayName":"树液","iconName":"Sap_Sprite"},"amount":1,"chance":2.5}]},{"key":"slimeEarth","displayName":"土原石粘液怪","description":null,"experience":10,"iconName":"Slime_Earth_Sprite","image":"Slime_Earth_2880x2160","dropRates":[{"item":{"id":"item_65108","displayName":"树液","iconName":"Sap_Sprite"},"amount":1,"chance":2.5}]},{"key":"slimeWater","displayName":"水原石粘液怪","description":null,"experience":10,"iconName":"Slime_Water_Sprite","image":"Slime_Water_2880x2160","dropRates":[{"item":{"id":"item_65108","displayName":"树液","iconName":"Sap_Sprite"},"amount":1,"chance":2.5}]},{"key":"slimeWind","displayName":"风原石粘液怪","description":null,"experience":10,"iconName":"Slime_Wind_Sprite","image":"Slime_Wind_2880x2160","dropRates":[{"item":{"id":"item_65108","displayName":"树液","iconName":"Sap_Sprite"},"amount":1,"chance":2.5}]},{"key":"slimeFire","displayName":"火原石粘液怪","description":null,"experience":10,"iconName":"Slime_Fire_Sprite","image":"Slime_Fire_2880x2160","dropRates":[{"item":{"id":"item_65108","displayName":"树液","iconName":"Sap_Sprite"},"amount":1,"chance":2.5}]},{"key":"bat","displayName":"蝙蝠怪","description":null,"experience":10,"iconName":"Bat_Sprite","image":"T_Bat","dropRates":[{"item":{"id":"item_65108","displayName":"树液","iconName":"Sap_Sprite"},"amount":1,"chance":2.5}]},{"key":"tuku","displayName":"磐石兽","description":null,"experience":10,"iconName":"Tuku_Tuku_Sprite","image":"Tuku_2880x2160","dropRates":[{"item":{"id":"item_65108","displayName":"树液","iconName":"Sap_Sprite"},"amount":1,"chance":2.5}]},{"key":"tukuBronze","displayName":"青铜石兽","description":null,"experience":10,"iconName":"Tuku_Tuku_Bronze_Sprite","image":"Tuku_Bronze_2880x2160","dropRates":[{"item":{"id":"item_65108","displayName":"树液","iconName":"Sap_Sprite"},"amount":1,"chance":2.5}]},{"key":"tukuSilver","displayName":"白银石兽","description":null,"experience":12,"iconName":"Tuku_Tuku_Silver_Sprite","image":"Tuku_Silver_2880x2160","dropRates":[{"item":{"id":"item_65108","displayName":"树液","iconName":"Sap_Sprite"},"amount":1,"chance":2.5}]},{"key":"tukuGold","displayName":"黄金石兽","description":null,"experience":12,"iconName":"Tuku_Tuku_Gold_Sprite","image":"Tuku_Gold_2880x2160","dropRates":[{"item":{"id":"item_65108","displayName":"树液","iconName":"Sap_Sprite"},"amount":1,"chance":2.5}]},{"key":"tukuOsmium","displayName":"锇石兽","description":null,"experience":15,"iconName":"Tuku_Tuku_Osmium_Sprite","image":"Tuku_Osmium_2880x2160","dropRates":[{"item":{"id":"item_65108","displayName":"树液","iconName":"Sap_Sprite"},"amount":1,"chance":2.5}]},{"key":"skully","displayName":"白骨妖","description":null,"experience":10,"iconName":"Skully_Sprite","image":"Skully_2880x2160","dropRates":[{"item":{"id":"item_65108","displayName":"树液","iconName":"Sap_Sprite"},"amount":1,"chance":2.5}]},{"key":"skully_earth","displayName":"春花白骨妖","description":null,"experience":10,"iconName":"Skully_Earth_Sprite","image":"Skully_Earth_2880x2160","dropRates":[{"item":{"id":"item_65108","displayName":"树液","iconName":"Sap_Sprite"},"amount":1,"chance":2.5}]},{"key":"skully_water","displayName":"冬寒白骨妖","description":null,"experience":10,"iconName":"Skully_Ice_Sprite","image":"Skully_Ice_2880x2160","dropRates":[{"item":{"id":"item_65108","displayName":"树液","iconName":"Sap_Sprite"},"amount":1,"chance":2.5}]},{"key":"skully_wind","displayName":"秋爽白骨妖","description":null,"experience":10,"iconName":"Skully_Wind_Sprite","image":"Skully_Wind_2880x2160","dropRates":[{"item":{"id":"item_65108","displayName":"树液","iconName":"Sap_Sprite"},"amount":1,"chance":2.5}]},{"key":"skully_fire","displayName":"夏炎白骨妖","description":null,"experience":10,"iconName":"Skully_Fire_Sprite","image":"Skully_Fire_2880x2160","dropRates":[{"item":{"id":"item_65108","displayName":"树液","iconName":"Sap_Sprite"},"amount":1,"chance":2.5}]},{"key":"snatcher","displayName":"百变猫","description":null,"experience":10,"iconName":"Snatcher_Sprite","image":"T_Snatcher","dropRates":[{"item":{"id":"item_65108","displayName":"树液","iconName":"Sap_Sprite"},"amount":1,"chance":2.5}]},{"key":"amalo","displayName":"犰狳怪","description":null,"experience":15,"iconName":"Amalo_Sprite","image":"T_Amalo","dropRates":[{"item":{"id":"item_65108","displayName":"树液","iconName":"Sap_Sprite"},"amount":1,"chance":2.5}]},{"key":"armolite","displayName":"龟龙兽","description":null,"experience":20,"iconName":"Armolite_Sprite","image":"T_Armulite","dropRates":[{"item":{"id":"item_65108","displayName":"树液","iconName":"Sap_Sprite"},"amount":1,"chance":2.5}]},{"key":"pickling","displayName":"异能毛毛虫","description":null,"experience":15,"iconName":"Pickling_Sprite","image":"T_Pickling","dropRates":[{"item":{"id":"item_65108","displayName":"树液","iconName":"Sap_Sprite"},"amount":1,"chance":2.5}]},{"key":"sphekter","displayName":"黄蜂怪","description":null,"experience":10,"iconName":"Sphekter_Sprite","image":"T_Spekhter","dropRates":[{"item":{"id":"item_65108","displayName":"树液","iconName":"Sap_Sprite"},"amount":1,"chance":2.5}]}],"usedToCraft":[{"key":"item_41200","displayName":"Candied tree seed","amount":1,"ingredients":[{"item":{"id":"item_65108","displayName":"树液","iconName":"Sap_Sprite"},"amount":1}],"genericIngredients":[{"key":"Generic_TreeSeed","amount":3,"genericItem":{"key":"Generic_TreeSeed","tags":["item.TreeSeed"],"iconName":"treeIcon_Sprite","displayName":"任意树木种子","items":[{"id":"item_21047","displayName":"枫树种子","iconName":"Maple_seeds_Sprite"},{"id":"item_21048","displayName":"橡树种子","iconName":"Oak_seeds_Sprite"},{"id":"item_21053","displayName":"桃花心木种子","iconName":"Mahogany_seeds_Sprite"},{"id":"item_21054","displayName":"白杨树种子","iconName":"Poplar_seeds_Sprite"},{"id":"item_21085","displayName":"蘑菇树种子","iconName":"Mushroom_tree_seeds_Sprite"},{"id":"item_21086","displayName":"月芽孢种子","iconName":"Wooblecap_seeds_Sprite"},{"id":"item_21087","displayName":"蘑菇伞","iconName":"Moonspore_seeds_Sprite"},{"id":"item_65001","displayName":"松果","iconName":"Pine_Cone_Sprite"}]}}],"category":"Misc","craftingUnlock":{"key":"item_41200","masteryLevel":1,"masteryType":"Foraging"},"item":{"id":"item_41200","displayName":"糖渍树木种子","price":70,"sellPrice":20,"sellAt":[],"stackable":true,"inventoryCategory":"Consumable","displayKey":"Consumable","description":"节俭的觅食者爱吃的食物。可制作。","qualities":{},"iconName":"Candied_Tree_Seed_Sprite","tags":["income.farming","Item.Consumable.Food","item.cooking.ingredient"]}},{"key":"item_65305","displayName":"Fertilizer I","amount":1,"ingredients":[{"item":{"id":"item_65300","displayName":"堆肥","iconName":"Compost_Sprite"},"amount":2},{"item":{"id":"item_65108","displayName":"树液","iconName":"Sap_Sprite"},"amount":1}],"genericIngredients":[],"category":"Farming","craftingUnlock":{"key":"item_65305","masteryLevel":1,"masteryType":"Farming"},"item":{"id":"item_65305","displayName":"化肥I","price":40,"sellPrice":7,"sellAt":[],"stackable":true,"inventoryCategory":"Farming","displayKey":"Farming","description":"如果与土壤混合，有一定几率能种植品质更好的农作物。","qualities":{},"iconName":"Fertilizer_I_Sprite","tags":[]}},{"key":"item_65306","displayName":"Fertilizer II","amount":1,"ingredients":[{"item":{"id":"item_65300","displayName":"堆肥","iconName":"Compost_Sprite"},"amount":2},{"item":{"id":"item_65108","displayName":"树液","iconName":"Sap_Sprite"},"amount":1},{"item":{"id":"item_62003","displayName":"银质海带","iconName":"Silver_Kelp_Sprite"},"amount":1}],"genericIngredients":[],"category":"Farming","craftingUnlock":{"key":"item_65306","masteryLevel":5,"masteryType":"Farming"},"item":{"id":"item_65306","displayName":"化肥II","price":70,"sellPrice":22,"sellAt":[],"stackable":true,"inventoryCategory":"Farming","displayKey":"Farming","description":"如果与土壤混合，有很大几率能种植品质更好的作物。","qualities":{},"iconName":"Fertilizer_II_Sprite","tags":[]}},{"key":"item_65307","displayName":"Fertilizer III","amount":1,"ingredients":[{"item":{"id":"item_65300","displayName":"堆肥","iconName":"Compost_Sprite"},"amount":3},{"item":{"id":"item_65108","displayName":"树液","iconName":"Sap_Sprite"},"amount":1},{"item":{"id":"item_62004","displayName":"锇质海带","iconName":"Osmium_Kelp_Sprite"},"amount":1}],"genericIngredients":[],"category":"Farming","craftingUnlock":{"key":"item_65307","masteryLevel":8,"masteryType":"Farming"},"item":{"id":"item_65307","displayName":"化肥III","price":390,"sellPrice":157,"sellAt":[],"stackable":true,"inventoryCategory":"Farming","displayKey":"Farming","description":"如果与土壤混合，将种植出品质更好的作物。","qualities":{},"iconName":"Fertilizer_III_Sprite","tags":[]}},{"key":"item_65299","displayName":"Compost bin","amount":1,"ingredients":[{"item":{"id":"item_65003","displayName":"木头","iconName":"Wood_Sprite"},"amount":20},{"item":{"id":"item_65052","displayName":"废品","iconName":"Trash_Sprite"},"amount":5},{"item":{"id":"item_65108","displayName":"树液","iconName":"Sap_Sprite"},"amount":5}],"genericIngredients":[],"category":"Artisan","craftingUnlock":{"key":"item_65299","masteryLevel":2,"masteryType":"Farming"},"item":{"id":"item_65299","displayName":"堆肥桶","price":200,"sellPrice":50,"sellAt":[],"stackable":true,"inventoryCategory":"ResourceEquipment","displayKey":"ResourceEquipment","description":"Compostbindesc","qualities":{},"iconName":"Compost_bin_Sprite","tags":[]}},{"key":"item_64005","displayName":"Ground insect scent","amount":2,"ingredients":[{"item":{"id":"item_65108","displayName":"树液","iconName":"Sap_Sprite"},"amount":5}],"genericIngredients":[{"key":"Generic_Flower","amount":1,"genericItem":{"key":"Generic_Flower","tags":["item.flower"],"iconName":"Any_flower_Sprite","displayName":"任何花卉","items":[{"id":"item_21013","displayName":"牡丹","iconName":"Peony_Sprite"},{"id":"item_21014","displayName":"雏菊","iconName":"Daisy_Sprite"},{"id":"item_21016","displayName":"雪滴花","iconName":"Snowdrop_Sprite"},{"id":"item_21045","displayName":"虞美人","iconName":"Poppy_Sprite"},{"id":"item_21077","displayName":"蓝铃花","iconName":"Bluebell_Blossom_Sprite"},{"id":"item_21080","displayName":"螺旋花","iconName":"Helixpur_Blossom_Sprite"},{"id":"item_21081","displayName":"海刺花","iconName":"Marinethorn_Blossom_Sprite"},{"id":"item_21084","displayName":"大丽香","iconName":"Petalia_Sprite"},{"id":"item_22014","displayName":"栀子花","iconName":"Gardenia_Sprite"},{"id":"item_22015","displayName":"向日葵","iconName":"Sunflower_Sprite"},{"id":"item_22016","displayName":"Rose","iconName":"Rose_Sprite"},{"id":"item_22017","displayName":"百合花","iconName":"Lily_Sprite"},{"id":"item_22018","displayName":"Iris","iconName":"Iris_Sprite"},{"id":"item_23014","displayName":"蓝色大丽花","iconName":"Blue_Dahlia_Sprite"},{"id":"item_23015","displayName":"仙人掌","iconName":"Cactus_Sprite"},{"id":"item_23016","displayName":"兰花","iconName":"Orchid_Sprite"},{"id":"item_23045","displayName":"仙女月季","iconName":"Fairy_Rose_Sprite"},{"id":"item_24001","displayName":"棉花","iconName":"Cotton_Sprite"},{"id":"item_51102","displayName":"油菜籽","iconName":"Canola_Sprite"},{"id":"item_51104","displayName":"郁金香","iconName":"Tulip_Sprite"},{"id":"item_51105","displayName":"紫罗兰","iconName":"Violet_Sprite"},{"id":"item_51106","displayName":"水仙花","iconName":"Daffodil_Sprite"},{"id":"item_52103","displayName":"科斯莫","iconName":"Cosmo_Sprite"},{"id":"item_52104","displayName":"翠雀花","iconName":"Larkspur_Sprite"},{"id":"item_52105","displayName":"芙蓉","iconName":"Hibiscus_Sprite"},{"id":"item_52106","displayName":"白色木槿花","iconName":"White_Hibiscus_Sprite"},{"id":"item_53103","displayName":"Lotus","iconName":"Lotus_Sprite"},{"id":"item_53107","displayName":"巨花魔芋","iconName":"Titan_Arum_Sprite"},{"id":"item_53108","displayName":"Jepun","iconName":"Jepun_Sprite"},{"id":"item_54104","displayName":"三色堇","iconName":"Pansy_Sprite"},{"id":"item_54105","displayName":"Rafflesia","iconName":"Rafflesia_Sprite"}]}}],"category":"Misc","craftingUnlock":{"key":"item_64005","masteryLevel":1,"masteryType":"Catching"},"item":{"id":"item_64005","displayName":"地面昆虫专用诱香","price":40,"sellPrice":10,"sellAt":[],"stackable":true,"inventoryCategory":"Consumable","displayKey":"Consumable","description":"一种可制作的诱香，能降低地面昆虫的警觉性。可以食用或附在陷阱上。","qualities":{},"iconName":"Ground_insect_scent__Sprite","tags":["Item.Consumable.Food","item.cooking.ingredient"]}},{"key":"Item_63032","displayName":"Glue trap","amount":2,"ingredients":[{"item":{"id":"item_65108","displayName":"树液","iconName":"Sap_Sprite"},"amount":5},{"item":{"id":"item_50505","displayName":"黑暗精华","iconName":"Dark_Essence_Sprite"},"amount":1}],"genericIngredients":[{"key":"Generic_Ore","amount":2,"genericItem":{"key":"Generic_Ore","tags":["item.ore"],"iconName":"T_AnyOre_Sprite","displayName":"任何矿石","items":[{"id":"item_61001","displayName":"铜矿石","iconName":"Bronze_Ore_Sprite"},{"id":"item_61002","displayName":"金矿石","iconName":"Gold_Ore_Sprite"},{"id":"item_61004","displayName":"锇矿石","iconName":"Osmium_Ore_Sprite"},{"id":"item_61045","displayName":"银矿石","iconName":"Silver_Ore_Sprite"}]}}],"category":"Misc","item":{"id":"item_63032","displayName":"胶水陷阱","price":80,"sellPrice":25,"sellAt":[],"stackable":true,"inventoryCategory":"Trap","displayKey":"Trap","description":"一种陷阱，可以将敌人黏住。","qualities":{},"iconName":"Glue_trap_Sprite","tags":[]}},{"key":"item_65008","displayName":"Ordinary scarecrow","amount":1,"ingredients":[{"item":{"id":"item_65003","displayName":"木头","iconName":"Wood_Sprite"},"amount":20},{"item":{"id":"item_65032","displayName":"纤维","iconName":"Fiber_Sprite"},"amount":20},{"item":{"id":"item_65108","displayName":"树液","iconName":"Sap_Sprite"},"amount":10}],"genericIngredients":[],"category":"Scarecrow","craftingUnlock":{"key":"item_65008","masteryLevel":4,"masteryType":"Farming"},"item":{"id":"item_65008","displayName":"普通稻草人","price":230,"sellPrice":90,"sellAt":[],"stackable":true,"inventoryCategory":"Farming","displayKey":"Farming","description":"阻止乌鸦扰乱庄稼。保护一个11x11的区域。","qualities":{},"iconName":"Ordinary_scarecrow_Sprite","tags":[]}},{"key":"item_65508","displayName":"Ocean guardian scarecrow","amount":1,"ingredients":[{"item":{"id":"item_65052","displayName":"废品","iconName":"Trash_Sprite"},"amount":30},{"item":{"id":"item_65004","displayName":"石头","iconName":"Stone_Sprite"},"amount":20},{"item":{"id":"item_65108","displayName":"树液","iconName":"Sap_Sprite"},"amount":10}],"genericIngredients":[],"category":"Scarecrow","item":{"id":"item_65508","displayName":"海洋战士稻草人","price":150,"sellPrice":60,"sellAt":[],"stackable":true,"inventoryCategory":"Farming","displayKey":"Farming","description":"防止乌鸦惊扰庄稼。保护一个11x11的区域。","qualities":{},"iconName":"Ocean_warrior_scarecrow_Sprite","tags":[]}},{"key":"item_65532","displayName":"Ocean Explorer scarecrow","amount":1,"ingredients":[{"item":{"id":"item_65003","displayName":"木头","iconName":"Wood_Sprite"},"amount":20},{"item":{"id":"item_65032","displayName":"纤维","iconName":"Fiber_Sprite"},"amount":20},{"item":{"id":"item_65108","displayName":"树液","iconName":"Sap_Sprite"},"amount":10}],"genericIngredients":[],"category":"Scarecrow","item":{"id":"item_65532","displayName":"海洋探险家稻草人","price":230,"sellPrice":90,"sellAt":[],"stackable":true,"inventoryCategory":"Farming","displayKey":"Farming","description":"防止乌鸦惊扰庄稼。保护一个11x11的区域。","qualities":{},"iconName":"Scout_scarecrow_Sprite","tags":[]}},{"key":"Item_65115","displayName":"Scrap scarecrow","amount":1,"ingredients":[{"item":{"id":"item_65107","displayName":"碎渣","iconName":"Scrap_Sprite"},"amount":10},{"item":{"id":"item_65052","displayName":"废品","iconName":"Trash_Sprite"},"amount":10},{"item":{"id":"item_65108","displayName":"树液","iconName":"Sap_Sprite"},"amount":10}],"genericIngredients":[],"category":"Scarecrow","item":{"id":"item_65115","displayName":"再生稻草人","price":600,"sellPrice":110,"sellAt":[],"stackable":true,"inventoryCategory":"Farming","displayKey":"Farming","description":"阻止乌鸦扰乱庄稼。保护一个11x11的区域。","qualities":{},"iconName":"Scrap_scarecrow_Sprite","tags":[]}}],"isUpgradeRequirement":[{"item":{"id":"item_65444","displayName":"昆虫屋","iconName":"Insect_house_Sprite2"},"price":10000,"daysDelay":1,"townRank":0,"tag":[],"priceOverride":7000,"priority":10,"requirements":[{"item":{"id":"item_65300","displayName":"堆肥","iconName":"Compost_Sprite"},"amount":20},{"item":{"id":"item_65063","displayName":"硬木","iconName":"HardWood_Sprite"},"amount":15},{"item":{"id":"item_65108","displayName":"树液","iconName":"Sap_Sprite"},"amount":10},{"item":{"id":"item_61006","displayName":"金锭","iconName":"Gold_Bar_Sprite"},"amount":1}],"unlockRequirements":[],"category":"None","customIcon":"/Game/ProjectCoral/Textures/AtlasImport/Frames/Items_Beehouse.Items_Beehouse","hardnessLevel":"Basic","toolType":"None","useCategory":true,"useCustomIcon":false,"shop":{"url":"carpenter","displayName":"Carpenter"}}],"requiredAsOffering":[{"key":"CropBased","offeringGroupTitle":"作物祭坛","urlPath":"cropaltar","offeringGroupRewardText":"解锁温室","offerings":[{"title":"关键资源","imageName":"Essential_Offerings","numOfItemRequired":5,"rewards":{"items":[{"item":{"id":"item_65049","displayName":"回收机","iconName":"Recycling_Machine_Sprite"},"amount":1}],"recipes":[]},"offeringType":"Temple","requiredItems":[{"item":{"id":"item_65003","displayName":"木头","iconName":"Wood_Sprite"},"amount":10,"quality":"base"},{"item":{"id":"item_65004","displayName":"石头","iconName":"Stone_Sprite"},"amount":10,"quality":"base"},{"item":{"id":"item_65032","displayName":"纤维","iconName":"Fiber_Sprite"},"amount":10,"quality":"base"},{"item":{"id":"item_65108","displayName":"树液","iconName":"Sap_Sprite"},"amount":10,"quality":"base"},{"item":{"id":"item_21047","displayName":"枫树种子","iconName":"Maple_seeds_Sprite"},"amount":5,"quality":"base"},{"item":{"id":"item_21048","displayName":"橡树种子","iconName":"Oak_seeds_Sprite"},"amount":5,"quality":"base"},{"item":{"id":"item_65001","displayName":"松果","iconName":"Pine_Cone_Sprite"},"amount":5,"quality":"base"}]}],"offeringType":"Temple"}]}