{"item":{"id":"item_65312","displayName":"DT_InventoryItems.item_65312_name","price":20,"sellPrice":8,"sellAt":[],"stackable":true,"inventoryCategory":"Farming","displayKey":"Farming","description":"DT_InventoryItems.item_65312_description","qualities":{},"iconName":"Hydro_II_Sprite","tags":[]},"craftedFrom":[{"key":"item_65312","displayName":"Hydro II","amount":1,"ingredients":[{"item":{"id":"item_65004","displayName":"DT_InventoryItems.item_65004_name","iconName":"Stone_Sprite"},"amount":2},{"item":{"id":"item_65300","displayName":"DT_InventoryItems.item_65300_name","iconName":"Compost_Sprite"},"amount":2}],"genericIngredients":[],"category":"Farming","craftingUnlock":{"key":"item_65312","masteryLevel":4,"masteryType":"Farming"},"item":{"id":"item_65312","displayName":"DT_InventoryItems.item_65312_name","price":20,"sellPrice":8,"sellAt":[],"stackable":true,"inventoryCategory":"Farming","displayKey":"Farming","description":"DT_InventoryItems.item_65312_description","qualities":{},"iconName":"Hydro_II_Sprite","tags":[]}}]}