{"item":{"id":"item_32013","displayName":"DT_InventoryItems.item_32013_name","price":1020,"sellPrice":715,"sellAt":["Sam"],"stackable":true,"inventoryCategory":"AnimalProduct","displayKey":"AnimalProduct","description":"DT_InventoryItems.item_32013_description","qualities":{"bronze":{"price":1170,"sellPrice":822},"silver":{"price":1320,"sellPrice":930},"gold":{"price":1530,"sellPrice":1073},"osmium":{"price":2040,"sellPrice":1430}},"iconName":"Large_gesha_coffee_bean_Sprite","tags":["income.ranching","item.townrank.5","item.animalproduct.coffeebean","Item.Consumable.Food","item.cooking.ingredient"]},"artisanResult":[{"useCategory":false,"day":0,"time":{"hours":11,"minutes":0},"additionalInput":[],"input":{"amount":1,"item":{"id":"item_32013","displayName":"DT_InventoryItems.item_32013_name","iconName":"Large_gesha_coffee_bean_Sprite"}},"output":{"amount":1,"item":{"id":"item_32013","displayName":"DT_InventoryItems.item_32013_name","iconName":"Large_gesha_coffee_bean_Sprite","sellPrice":715}},"genericInput":null,"refinements":[{"from":"silver","to":"gold","day":0,"time":{"hours":14,"minutes":0}},{"from":"gold","to":"osmium","day":0,"time":{"hours":18,"minutes":0}}],"machine":"SlimeOfTransmutation"}],"artisanIngredient":[{"useCategory":false,"day":0,"time":{"hours":5,"minutes":0},"additionalInput":[],"input":{"amount":1,"item":{"id":"item_32013","displayName":"DT_InventoryItems.item_32013_name","iconName":"Large_gesha_coffee_bean_Sprite"}},"output":{"amount":1,"item":{"id":"item_41052","displayName":"DT_InventoryItems.item_41052_name","iconName":"Large_gesha_coffee_Sprite","sellPrice":1430}},"genericInput":null,"machine":"Keg"},{"useCategory":false,"day":0,"time":{"hours":11,"minutes":0},"additionalInput":[],"input":{"amount":1,"item":{"id":"item_32013","displayName":"DT_InventoryItems.item_32013_name","iconName":"Large_gesha_coffee_bean_Sprite"}},"output":{"amount":1,"item":{"id":"item_32013","displayName":"DT_InventoryItems.item_32013_name","iconName":"Large_gesha_coffee_bean_Sprite","sellPrice":715}},"genericInput":null,"refinements":[{"from":"silver","to":"gold","day":0,"time":{"hours":14,"minutes":0}},{"from":"gold","to":"osmium","day":0,"time":{"hours":18,"minutes":0}}],"machine":"SlimeOfTransmutation"}],"usedToCook":[{"key":"item_80088","amount":1,"cookingKey":"StoneSoup","item":{"id":"item_80088","displayName":"DT_InventoryItems.item_80088_name","price":50,"sellPrice":5,"sellAt":[],"stackable":true,"inventoryCategory":"Consumable","displayKey":"Consumable","description":"DT_InventoryItems.item_80088_description","qualities":{"bronze":{"price":58,"sellPrice":6},"silver":{"price":63,"sellPrice":6},"gold":{"price":75,"sellPrice":8},"osmium":{"price":100,"sellPrice":10}},"iconName":"Stone_Soup_Sprite","tags":["income.other","Item.Consumable.Food","item.cooking.ingredient"]},"craftingUnlock":{"key":"item_80088","masteryLevel":4,"masteryType":"Mining"},"utensils":["Pot"],"genericIngredients":[{"amount":1,"genericItem":{"key":"Any_Edible","tags":["Item.Consumable.Drink","Item.Consumable.Food"],"iconName":"T_AnyIngridient_Sprite","displayName":"E1AAD9604F670830741E3B831DAFE9CF"},"key":"Any_Edible"}],"ingredients":[{"item":{"id":"item_65004","displayName":"DT_InventoryItems.item_65004_name","iconName":"Stone_Sprite"},"amount":1}],"eitherOrIngredients":[[{"item":{"id":"item_41180","displayName":"DT_InventoryItems.item_41180_name","iconName":"Goat_Yoghurt_Sprite"},"amount":1},{"item":{"id":"item_41181","displayName":"DT_InventoryItems.item_41181_name","iconName":"Large_Goat_Yoghurt_Sprite"},"amount":1}]]}],"asGift":[{"pref":{"icon":"T_Icon_Love","label":"Love","preferenceField":"lovePreferences"},"npcs":[{"key":"Raj","characterName":"Raj","iconName":"Icon_raj"}]}],"requiredAsOffering":[{"key":"RareBased","offeringGroupTitle":"AB32B73C46F3C09E448A1790B7F2AEAD","urlPath":"rarealtar","offeringGroupRewardText":"FBDE8BED483541AF46A06EACF51AA687","offerings":[{"title":"771782814413A0C21F89DFADAFD48D5C","imageName":"Rare_Animals_Offerings","numOfItemRequired":-1,"rewards":{"items":[{"item":{"id":"item_65509","displayName":"DT_InventoryItems.item_65509_name","iconName":"Auto_Petter_Sprite"},"amount":1}],"recipes":[]},"offeringType":"Temple","requiredItems":[{"item":{"id":"item_31001","displayName":"DT_InventoryItems.item_31001_name","iconName":"Black_Truffle_Sprite"},"amount":1,"quality":"base"},{"item":{"id":"item_32018","displayName":"DT_InventoryItems.item_32018_name","iconName":"Large_quail_egg_Sprite"},"amount":1,"quality":"base"},{"item":{"id":"item_32011","displayName":"DT_InventoryItems.item_32011_name","iconName":"Large_llama_wool_Sprite"},"amount":1,"quality":"base"},{"item":{"id":"item_32015","displayName":"DT_InventoryItems.item_32015_name","iconName":"Large_feather_Sprite"},"amount":1,"quality":"base"},{"item":{"id":"item_32013","displayName":"DT_InventoryItems.item_32013_name","iconName":"Large_gesha_coffee_bean_Sprite"},"amount":1,"quality":"base"}]}],"offeringType":"Temple"}],"consumables":{"bronze":{"key":"item_32013-a","bVaryHealthToMax":false,"healthDelta":-23,"bVaryStaminaToMax":false,"staminaDelta":52,"level":0,"overwriteDuration":false,"duration":0,"buff":"None","itemType":"Food"},"gold":{"key":"item_32013-c","bVaryHealthToMax":false,"healthDelta":-17,"bVaryStaminaToMax":false,"staminaDelta":68,"level":0,"overwriteDuration":false,"duration":0,"buff":"None","itemType":"Food"},"silver":{"key":"item_32013-b","bVaryHealthToMax":false,"healthDelta":-20,"bVaryStaminaToMax":false,"staminaDelta":56,"level":0,"overwriteDuration":false,"duration":0,"buff":"None","itemType":"Food"},"osmium":{"key":"item_32013-d","bVaryHealthToMax":false,"healthDelta":0,"bVaryStaminaToMax":false,"staminaDelta":90,"level":0,"overwriteDuration":false,"duration":0,"buff":"None","itemType":"Food"},"base":{"key":"item_32013","bVaryHealthToMax":false,"healthDelta":-30,"bVaryStaminaToMax":false,"staminaDelta":45,"level":0,"overwriteDuration":false,"duration":0,"buff":"None","itemType":"Food"}},"producedByAnimal":{"key":"Luwak","variants":[{"variant":"Default","icons":{"adult":"Luwak_Sprite"}}],"building":"BarnLvl2","daysToGrow":43,"harvestCooldown":2,"animalProduceType":"DropInAllDay","baseProduceDropChance":10,"incrementProduceDropChance":2,"produceDropLocation":"OutsideBuildingOnly","produces":[{"minimumFriendshipLevelToSpawn":0,"small":{"id":"item_32003","displayName":"DT_InventoryItems.item_32003_name","iconName":"Gesha_coffee_bean_Sprite"},"large":{"id":"item_32013","displayName":"DT_InventoryItems.item_32013_name","iconName":"Large_gesha_coffee_bean_Sprite"}}],"displayName":"7FB2829E4D6383B6D9D536BF8883185B"}}