{"item":{"id":"item_61006","displayName":"Batang emas","price":7500,"sellPrice":250,"sellAt":["Blacksmith"],"stackable":true,"inventoryCategory":"Resource","displayKey":"Resource","description":"Sebatang emas.","qualities":{},"iconName":"Gold_Bar_Sprite","tags":["income.mining"]},"artisanResult":[{"useCategory":false,"day":0,"time":{"hours":3,"minutes":0},"additionalInput":[{"amount":1,"item":{"id":"item_65006","displayName":"Batu bara","iconName":"Coal_Sprite"}}],"input":{"amount":5,"item":{"id":"item_61002","displayName":"Bijih emas","iconName":"Gold_Ore_Sprite"}},"output":{"amount":1,"item":{"id":"item_61006","displayName":"Batang emas","iconName":"Gold_Bar_Sprite","sellPrice":250}},"genericInput":null,"machine":"furnace"},{"useCategory":false,"day":1,"time":{"hours":12,"minutes":0},"additionalInput":[],"input":{"amount":1,"item":{"id":"item_61006","displayName":"Batang emas","iconName":"Gold_Bar_Sprite"}},"output":{"amount":2,"item":{"id":"item_61006","displayName":"Batang emas","iconName":"Gold_Bar_Sprite","sellPrice":250}},"genericInput":null,"machine":"SlimeOfReplicator"},{"useCategory":false,"day":0,"time":{"hours":6,"minutes":0},"additionalInput":[],"input":{"amount":3,"item":{"id":"item_61044","displayName":"Bar perak","iconName":"Silver_Bar_Sprite"}},"output":{"amount":1,"item":{"id":"item_61006","displayName":"Batang emas","iconName":"Gold_Bar_Sprite","sellPrice":250}},"genericInput":null,"machine":"SlimeOfTransmutation"}],"artisanIngredient":[{"useCategory":false,"day":1,"time":{"hours":12,"minutes":0},"additionalInput":[],"input":{"amount":1,"item":{"id":"item_61006","displayName":"Batang emas","iconName":"Gold_Bar_Sprite"}},"output":{"amount":2,"item":{"id":"item_61006","displayName":"Batang emas","iconName":"Gold_Bar_Sprite","sellPrice":250}},"genericInput":null,"machine":"SlimeOfReplicator"},{"useCategory":false,"day":0,"time":{"hours":6,"minutes":0},"additionalInput":[],"input":{"amount":3,"item":{"id":"item_61006","displayName":"Batang emas","iconName":"Gold_Bar_Sprite"}},"output":{"amount":1,"item":{"id":"item_61008","displayName":"Batang osmium","iconName":"Osmium_Bar_Sprite","sellPrice":750}},"genericInput":null,"machine":"SlimeOfTransmutation"}],"usedToCraft":[{"key":"item_65122","displayName":"Deluxe chest","amount":1,"ingredients":[{"item":{"id":"item_65063","displayName":"Kayu keras","iconName":"HardWood_Sprite"},"amount":30},{"item":{"id":"item_61006","displayName":"Batang emas","iconName":"Gold_Bar_Sprite"},"amount":3}],"genericIngredients":[],"category":"Farming","item":{"id":"item_65122","displayName":"Peti Mewah","price":5630,"sellPrice":2250,"sellAt":[],"stackable":true,"inventoryCategory":"Farming","displayKey":"Farming","description":"Penyimpanan untuk semua jenis item. Dapat ditempatkan di sekitar pulau, dan menahan hingga 40 benda.","qualities":{},"iconName":"Deluxe_Chest_Sprite","tags":[]}},{"key":"item_65019","displayName":"Loom","amount":1,"ingredients":[{"item":{"id":"item_65107","displayName":"Kepingan","iconName":"Scrap_Sprite"},"amount":25},{"item":{"id":"item_65003","displayName":"Kayu","iconName":"Wood_Sprite"},"amount":30},{"item":{"id":"item_61006","displayName":"Batang emas","iconName":"Gold_Bar_Sprite"},"amount":4}],"genericIngredients":[],"category":"Artisan","craftingUnlock":{"key":"item_65019","masteryLevel":6,"masteryType":"Ranching"},"item":{"id":"item_65019","displayName":"Mesin tenun","price":4000,"sellPrice":1135,"sellAt":[],"stackable":true,"inventoryCategory":"Artisan equipment","displayKey":"ArtisanEquipment","description":"Mengubah wol menjadi kain.","qualities":{},"iconName":"Loom_Sprite","tags":[]}},{"key":"item_65021","displayName":"Oil press","amount":1,"ingredients":[{"item":{"id":"item_65107","displayName":"Kepingan","iconName":"Scrap_Sprite"},"amount":30},{"item":{"id":"item_65202","displayName":"Kaca","iconName":"Glass_Sprite"},"amount":20},{"item":{"id":"item_61006","displayName":"Batang emas","iconName":"Gold_Bar_Sprite"},"amount":2},{"item":{"id":"item_65063","displayName":"Kayu keras","iconName":"HardWood_Sprite"},"amount":2}],"genericIngredients":[],"category":"Artisan","craftingUnlock":{"key":"item_65021","masteryLevel":8,"masteryType":"Foraging"},"item":{"id":"item_65021","displayName":"Press Minyak","price":3000,"sellPrice":890,"sellAt":[],"stackable":true,"inventoryCategory":"Artisan equipment","displayKey":"ArtisanEquipment","description":"Digunakan untuk membuat semua jenis minyak.","qualities":{},"iconName":"Oil_press_Sprite","tags":[]}},{"key":"item_65268","displayName":"Slime of replication","amount":1,"ingredients":[{"item":{"id":"item_50506","displayName":"Slime Goop","iconName":"Slime_goop_Sprite"},"amount":20},{"item":{"id":"item_61006","displayName":"Batang emas","iconName":"Gold_Bar_Sprite"},"amount":5},{"item":{"id":"item_62008","displayName":"Saripati kelp osmium","iconName":"Osmium_Kelp_Essence_Sprite"},"amount":2},{"item":{"id":"item_65202","displayName":"Kaca","iconName":"Glass_Sprite"},"amount":30}],"genericIngredients":[],"category":"Artisan","craftingUnlock":{"key":"item_65268","masteryLevel":10,"masteryType":"Combat"},"item":{"id":"item_65268","displayName":"S.O.R.","price":16000,"sellPrice":4750,"sellAt":[],"stackable":true,"inventoryCategory":"Artisan equipment","displayKey":"ArtisanEquipment","description":"Lendir replikasi ini dapat menduplikasi item. Berikan saja tiga hari atau lebih.","qualities":{},"iconName":"Slime_of_replication_Sprite","tags":[]}},{"key":"item_65316","displayName":"Slime of transmutation","amount":1,"ingredients":[{"item":{"id":"item_50506","displayName":"Slime Goop","iconName":"Slime_goop_Sprite"},"amount":20},{"item":{"id":"item_61006","displayName":"Batang emas","iconName":"Gold_Bar_Sprite"},"amount":5},{"item":{"id":"item_61008","displayName":"Batang osmium","iconName":"Osmium_Bar_Sprite"},"amount":2},{"item":{"id":"item_65202","displayName":"Kaca","iconName":"Glass_Sprite"},"amount":30}],"genericIngredients":[],"category":"Artisan","craftingUnlock":{"key":"item_65316","masteryLevel":8,"masteryType":"Combat"},"item":{"id":"item_65316","displayName":"Slime transmutasi","price":11000,"sellPrice":3250,"sellAt":[],"stackable":true,"inventoryCategory":"Artisan equipment","displayKey":"ArtisanEquipment","description":"Tempatkan item untuk meningkatkan kualitasnya.","qualities":{},"iconName":"Slime_of_transmutation_Sprite","tags":[]}},{"key":"item_65303","displayName":"Solar panel","amount":1,"ingredients":[{"item":{"id":"item_65107","displayName":"Kepingan","iconName":"Scrap_Sprite"},"amount":20},{"item":{"id":"item_61006","displayName":"Batang emas","iconName":"Gold_Bar_Sprite"},"amount":3},{"item":{"id":"item_65202","displayName":"Kaca","iconName":"Glass_Sprite"},"amount":20}],"genericIngredients":[],"category":"Artisan","craftingUnlock":{"key":"item_65303","masteryLevel":7,"masteryType":"Diving"},"item":{"id":"item_65303","displayName":"Panel surya","price":3000,"sellPrice":1010,"sellAt":[],"stackable":true,"inventoryCategory":"Resource equipment","displayKey":"ResourceEquipment","description":"A solar-powered battery converter. It needs to be placed outdoors to harness sunlight and convert it into battery.","qualities":{},"iconName":"Solar_Panel_Sprite","tags":[]}},{"key":"item_65338","displayName":"Auto fertilizer","amount":1,"ingredients":[{"item":{"id":"item_65107","displayName":"Kepingan","iconName":"Scrap_Sprite"},"amount":20},{"item":{"id":"item_62007","displayName":"Saripati kelp perak","iconName":"Silver_Kelp_Essence_Sprite"},"amount":1},{"item":{"id":"item_61006","displayName":"Batang emas","iconName":"Gold_Bar_Sprite"},"amount":1},{"item":{"id":"item_65005","displayName":"Baterai","iconName":"Battery_Sprite"},"amount":1}],"genericIngredients":[],"category":"Farming","item":{"id":"item_65338","displayName":"Tambahan sprinkler A","price":580,"sellPrice":350,"sellAt":[],"stackable":true,"inventoryCategory":"Farming","displayKey":"Farming","description":"Tambahan untuk sprinkler. Secara otomatis menerapkan pupuk untuk benih terdekat saat dimuat dengannya.","qualities":{},"iconName":"Auto_fertilizer_Sprite","tags":[]}},{"key":"item_65339","displayName":"Auto seed","amount":1,"ingredients":[{"item":{"id":"item_65107","displayName":"Kepingan","iconName":"Scrap_Sprite"},"amount":20},{"item":{"id":"item_62006","displayName":"Saripati kelp Emas","iconName":"Gold_Kelp_Essence_Sprite"},"amount":1},{"item":{"id":"item_61006","displayName":"Batang emas","iconName":"Gold_Bar_Sprite"},"amount":1},{"item":{"id":"item_65005","displayName":"Baterai","iconName":"Battery_Sprite"},"amount":1}],"genericIngredients":[],"category":"Farming","item":{"id":"item_65339","displayName":"Tambahan sprinkler B","price":1330,"sellPrice":800,"sellAt":[],"stackable":true,"inventoryCategory":"Farming","displayKey":"Farming","description":"Tambahan untuk sprinkler. Secara otomatis menanam benih untuk mengosongkan tanah yang dikosongkan saat dimuat dengannya.","qualities":{},"iconName":"Auto_seed_Sprite","tags":[]}},{"key":"item_63040","displayName":"Flying insect trap","amount":1,"ingredients":[{"item":{"id":"item_61006","displayName":"Batang emas","iconName":"Gold_Bar_Sprite"},"amount":1},{"item":{"id":"item_65202","displayName":"Kaca","iconName":"Glass_Sprite"},"amount":1}],"genericIngredients":[{"key":"Any_Honey","amount":1,"genericItem":{"key":"Any_Honey","tags":["item.artisan.honey"],"iconName":"T_AnyHoney_Sprite","displayName":"Madu apa pun","items":[{"id":"item_41076","displayName":"Madu kaktus","iconName":"Honey_Sprite"},{"id":"item_41148","displayName":"Madu daisy","iconName":"Honey_Sprite"},{"id":"item_41149","displayName":"Madu peony","iconName":"Honey_Sprite"},{"id":"item_41150","displayName":"Madu poppy","iconName":"Honey_Sprite"},{"id":"item_41151","displayName":"Madu snowdrop","iconName":"Honey_Sprite"},{"id":"item_41152","displayName":"Madu bunga matahari","iconName":"Honey_Sprite"},{"id":"item_41153","displayName":"Madu gardenia","iconName":"Honey_Sprite"},{"id":"item_41154","displayName":"Madu mawar","iconName":"Honey_Sprite"},{"id":"item_41155","displayName":"Madu lily","iconName":"Honey_Sprite"},{"id":"item_41156","displayName":"Madu iris","iconName":"Honey_Sprite"},{"id":"item_41157","displayName":"Madu anggrek","iconName":"Honey_Sprite"},{"id":"item_41158","displayName":"Madu dahlia biru","iconName":"Honey_Sprite"},{"id":"item_41159","displayName":"Tulip madu","iconName":"Honey_Sprite"},{"id":"item_41160","displayName":"Madu violet","iconName":"Honey_Sprite"},{"id":"item_41161","displayName":"Madu daffodil","iconName":"Honey_Sprite"},{"id":"item_41162","displayName":"Madu Kanola","iconName":"Honey_Sprite"},{"id":"item_41163","displayName":"Madu hibiscus putih","iconName":"Honey_Sprite"},{"id":"item_41164","displayName":"Madu lakspur","iconName":"Honey_Sprite"},{"id":"item_41165","displayName":"Madu cosmo","iconName":"Honey_Sprite"},{"id":"item_41166","displayName":"Madu hibiscus","iconName":"Honey_Sprite"},{"id":"item_41167","displayName":"Madu teratai","iconName":"Honey_Sprite"},{"id":"item_41170","displayName":"Madu jepun","iconName":"Honey_Sprite"},{"id":"item_41171","displayName":"Madu pansy","iconName":"Honey_Sprite"},{"id":"item_41184","displayName":"Madu mawar peri","iconName":"Honey_Sprite"}]}}],"category":"Misc","craftingUnlock":{"key":"item_63040","masteryLevel":6,"masteryType":"Catching"},"item":{"id":"item_63040","displayName":"Perangkap serangga terbang","price":1060,"sellPrice":305,"sellAt":[],"stackable":true,"inventoryCategory":"Trap","displayKey":"Trap","description":"Sebuah jebakan.","qualities":{},"iconName":"Flying_insect_trap_Sprite","tags":[]}},{"key":"item_63044","displayName":"Float trap","amount":1,"ingredients":[{"item":{"id":"item_61006","displayName":"Batang emas","iconName":"Gold_Bar_Sprite"},"amount":1},{"item":{"id":"item_65202","displayName":"Kaca","iconName":"Glass_Sprite"},"amount":1}],"genericIngredients":[{"key":"Any_DriedScavengables","amount":1,"genericItem":{"key":"Any_DriedScavengables","tags":["item.artisan.DriedScavengeables"],"iconName":"Seafood_jerky","displayName":"Barang Temuan Kering Apa Pun","items":[{"id":"item_41295","displayName":"Kerang kapal uap kering","iconName":"Seafood_jerky_Sprite"},{"id":"item_41296","displayName":"Kerang darah kering","iconName":"Seafood_jerky_Sprite"},{"id":"item_41297","displayName":"Kerang jackknife kering","iconName":"Seafood_jerky_Sprite"},{"id":"item_41298","displayName":"Kerang cherrystone kering","iconName":"Seafood_jerky_Sprite"},{"id":"item_41299","displayName":"Shell pena amber kering","iconName":"Seafood_jerky_Sprite"},{"id":"item_41300","displayName":"Barnacle Gooseneck kering","iconName":"Seafood_jerky_Sprite"},{"id":"item_41301","displayName":"Kerang pisau cukur kering","iconName":"Seafood_jerky_Sprite"},{"id":"item_41302","displayName":"Quahog kering","iconName":"Seafood_jerky_Sprite"},{"id":"item_41303","displayName":"Geoduck kering","iconName":"Seafood_jerky_Sprite"},{"id":"item_41304","displayName":"Jamur laut kering","iconName":"Seafood_jerky_Sprite"},{"id":"item_41305","displayName":"Kerang bebek kering","iconName":"Seafood_jerky_Sprite"},{"id":"item_41306","displayName":"Kerang zebra kering","iconName":"Seafood_jerky_Sprite"},{"id":"item_41307","displayName":"Kerang biru kering","iconName":"Seafood_jerky_Sprite"},{"id":"item_41308","displayName":"Kerang bibir hijau kering","iconName":"Seafood_jerky_Sprite"},{"id":"item_41309","displayName":"Kerang kuda kering","iconName":"Seafood_jerky_Sprite"},{"id":"item_41310","displayName":"Oyster Pasifik kering","iconName":"Seafood_jerky_Sprite"},{"id":"item_41311","displayName":"Tiram timur kering","iconName":"Seafood_jerky_Sprite"},{"id":"item_41312","displayName":"Oyster Belon kering","iconName":"Seafood_jerky_Sprite"},{"id":"item_41313","displayName":"Oyster biru kering","iconName":"Seafood_jerky_Sprite"},{"id":"item_41314","displayName":"Tiram kumamoto kering","iconName":"Seafood_jerky_Sprite"},{"id":"item_41315","displayName":"Oyster Olympia kering","iconName":"Seafood_jerky_Sprite"},{"id":"item_41316","displayName":"Kerang Mediterania kering","iconName":"Seafood_jerky_Sprite"},{"id":"item_41317","displayName":"Kerang Calico kering","iconName":"Seafood_jerky_Sprite"},{"id":"item_41318","displayName":"Kerang bay kering","iconName":"Seafood_jerky_Sprite"},{"id":"item_41319","displayName":"Kerang Patagonian kering","iconName":"Seafood_jerky_Sprite"},{"id":"item_41320","displayName":"Scallop ratu kering","iconName":"Seafood_jerky_Sprite"},{"id":"item_41321","displayName":"Scallop raja kering","iconName":"Seafood_jerky_Sprite"},{"id":"item_41322","displayName":"Keripik rumput laut","iconName":"Seafood_jerky_Sprite"},{"id":"item_41323","displayName":"Keripik arame","iconName":"Seafood_jerky_Sprite"},{"id":"item_41324","displayName":"Keripik kombu","iconName":"Seafood_jerky_Sprite"},{"id":"item_41325","displayName":"Keripik selada laut","iconName":"Seafood_jerky_Sprite"},{"id":"item_41326","displayName":"Keripik anggur laut","iconName":"Seafood_jerky_Sprite"},{"id":"item_41327","displayName":"Landak laut hitam kering","iconName":"Seafood_jerky_Sprite"},{"id":"item_41328","displayName":"Urchin ungu kering","iconName":"Seafood_jerky_Sprite"},{"id":"item_41329","displayName":"Landak laut hijau kering","iconName":"Seafood_jerky_Sprite"},{"id":"item_41330","displayName":"Landak laut merah kering","iconName":"Seafood_jerky_Sprite"},{"id":"item_41331","displayName":"Burchin hati kering","iconName":"Seafood_jerky_Sprite"}]}}],"category":"Misc","craftingUnlock":{"key":"item_63044","masteryLevel":8,"masteryType":"Catching"},"item":{"id":"item_63044","displayName":"Perangkap apung","price":1060,"sellPrice":265,"sellAt":[],"stackable":true,"inventoryCategory":"Trap","displayKey":"Trap","description":"Sebuah jebakan.","qualities":{},"iconName":"Float_trap_Sprite","tags":[]}},{"key":"item_65530","displayName":"Auto harvest","amount":1,"ingredients":[{"item":{"id":"item_65107","displayName":"Kepingan","iconName":"Scrap_Sprite"},"amount":20},{"item":{"id":"item_62006","displayName":"Saripati kelp Emas","iconName":"Gold_Kelp_Essence_Sprite"},"amount":1},{"item":{"id":"item_61006","displayName":"Batang emas","iconName":"Gold_Bar_Sprite"},"amount":1},{"item":{"id":"item_65005","displayName":"Baterai","iconName":"Battery_Sprite"},"amount":1}],"genericIngredients":[],"category":"Farming","item":{"id":"item_65530","displayName":"Panen mobil","price":4920,"sellPrice":2950,"sellAt":[],"stackable":true,"inventoryCategory":"Farming","displayKey":"Farming","description":"Tambahan sprinkler. Secara otomatis memanen tanaman.","qualities":{},"iconName":"Auto_harvest_Sprite","tags":[]}}],"asGift":[{"pref":{"icon":"T_Icon_Hate","label":"Hate","preferenceField":"hatePreferences"},"npcs":[{"key":"Leah","characterName":"Leah","iconName":"Icon_leah"},{"key":"Lily","characterName":"Lily","iconName":"Icon_lily"},{"key":"Noah","characterName":"Noah","iconName":"Icon_noah"}]}],"isUpgradeRequirement":[{"item":{"id":"item_65069","displayName":"Kapak emas","iconName":"Gold_axe_Sprite"},"price":10000,"daysDelay":2,"townRank":0,"tag":[],"priceOverride":0,"priority":0,"requirements":[{"item":{"id":"item_65070","displayName":"Kapak perak","iconName":"Silver_axe_Sprite"},"amount":1},{"item":{"id":"item_61006","displayName":"Batang emas","iconName":"Gold_Bar_Sprite"},"amount":3},{"item":{"id":"item_65063","displayName":"Kayu keras","iconName":"HardWood_Sprite"},"amount":5}],"unlockRequirements":[{"item":{"id":"item_65070","displayName":"Kapak perak","iconName":"Silver_axe_Sprite"},"amount":1}],"category":"Tool","customIcon":null,"hardnessLevel":"Gold","toolType":"Axe","useCategory":true,"useCustomIcon":false,"shop":{"url":"blacksmith","displayName":"Blacksmith"}},{"item":{"id":"item_65077","displayName":"Cangkul emas","iconName":"Gold_hoe_Sprite"},"price":10000,"daysDelay":2,"townRank":0,"tag":[],"priceOverride":0,"priority":1,"requirements":[{"item":{"id":"item_65078","displayName":"Cangkul perak","iconName":"Silver_hoe_Sprite"},"amount":1},{"item":{"id":"item_61006","displayName":"Batang emas","iconName":"Gold_Bar_Sprite"},"amount":3},{"item":{"id":"item_65063","displayName":"Kayu keras","iconName":"HardWood_Sprite"},"amount":5}],"unlockRequirements":[{"item":{"id":"item_65078","displayName":"Cangkul perak","iconName":"Silver_hoe_Sprite"},"amount":1}],"category":"Tool","customIcon":null,"hardnessLevel":"Gold","toolType":"Hoe","useCategory":true,"useCustomIcon":false,"shop":{"url":"blacksmith","displayName":"Blacksmith"}},{"item":{"id":"item_65065","displayName":"Beliung emas","iconName":"Gold_pickaxe_Sprite"},"price":10000,"daysDelay":2,"townRank":0,"tag":[],"priceOverride":0,"priority":2,"requirements":[{"item":{"id":"item_65066","displayName":"Beliung perak","iconName":"Silver_pickaxe_Sprite"},"amount":1},{"item":{"id":"item_61006","displayName":"Batang emas","iconName":"Gold_Bar_Sprite"},"amount":3},{"item":{"id":"item_65063","displayName":"Kayu keras","iconName":"HardWood_Sprite"},"amount":5}],"unlockRequirements":[{"item":{"id":"item_65066","displayName":"Beliung perak","iconName":"Silver_pickaxe_Sprite"},"amount":1}],"category":"Tool","customIcon":null,"hardnessLevel":"Gold","toolType":"Pickaxe","useCategory":true,"useCustomIcon":false,"shop":{"url":"blacksmith","displayName":"Blacksmith"}},{"item":{"id":"item_65073","displayName":"Gembor emas","iconName":"Gold_watering_can_Sprite"},"price":10000,"daysDelay":2,"townRank":0,"tag":[],"priceOverride":0,"priority":4,"requirements":[{"item":{"id":"item_65074","displayName":"Gembor perak","iconName":"Silver_watering_can_Sprite"},"amount":1},{"item":{"id":"item_61006","displayName":"Batang emas","iconName":"Gold_Bar_Sprite"},"amount":3},{"item":{"id":"item_41029","displayName":"Damar","iconName":"Resin_Sprite"},"amount":3}],"unlockRequirements":[{"item":{"id":"item_65074","displayName":"Gembor perak","iconName":"Silver_watering_can_Sprite"},"amount":1}],"category":"Tool","customIcon":null,"hardnessLevel":"Gold","toolType":"WateringCan","useCategory":true,"useCustomIcon":false,"shop":{"url":"blacksmith","displayName":"Blacksmith"}},{"item":{"id":"item_65081","displayName":"Sabit emas","iconName":"Gold_scythe_Sprite"},"price":10000,"daysDelay":2,"townRank":0,"tag":[],"priceOverride":0,"priority":3,"requirements":[{"item":{"id":"item_65082","displayName":"Sabit perak","iconName":"Silver_scythe_Sprite"},"amount":1},{"item":{"id":"item_61006","displayName":"Batang emas","iconName":"Gold_Bar_Sprite"},"amount":3},{"item":{"id":"item_65063","displayName":"Kayu keras","iconName":"HardWood_Sprite"},"amount":5}],"unlockRequirements":[{"item":{"id":"item_65082","displayName":"Sabit perak","iconName":"Silver_scythe_Sprite"},"amount":1}],"category":"Tool","customIcon":null,"hardnessLevel":"Gold","toolType":"Scythe","useCategory":true,"useCustomIcon":false,"shop":{"url":"blacksmith","displayName":"Blacksmith"}},{"item":{"id":"item_110006","displayName":"Kandang ayam (Level 3)","iconName":"placeholder_icon"},"price":9000,"daysDelay":2,"townRank":0,"tag":[],"priceOverride":0,"priority":2,"requirements":[{"item":{"id":"item_65063","displayName":"Kayu keras","iconName":"HardWood_Sprite"},"amount":100},{"item":{"id":"item_65004","displayName":"Batu","iconName":"Stone_Sprite"},"amount":200},{"item":{"id":"item_61006","displayName":"Batang emas","iconName":"Gold_Bar_Sprite"},"amount":5},{"item":{"id":"item_65032","displayName":"Serat","iconName":"Fiber_Sprite"},"amount":50}],"unlockRequirements":[{"item":{"id":"item_110004","displayName":"Cetak biru kandang ayam level 1","iconName":"Coop_level_1_blueprint_Sprite"},"amount":1}],"category":"None","customIcon":null,"hardnessLevel":"Basic","toolType":"None","useCategory":true,"useCustomIcon":false,"shop":{"url":"carpenter","displayName":"Carpenter"}},{"item":{"id":"item_110003","displayName":"Lumbung (level 3)","iconName":"placeholder_icon"},"price":15000,"daysDelay":2,"townRank":0,"tag":[],"priceOverride":0,"priority":4,"requirements":[{"item":{"id":"item_65063","displayName":"Kayu keras","iconName":"HardWood_Sprite"},"amount":200},{"item":{"id":"item_65004","displayName":"Batu","iconName":"Stone_Sprite"},"amount":300},{"item":{"id":"item_61006","displayName":"Batang emas","iconName":"Gold_Bar_Sprite"},"amount":5},{"item":{"id":"item_65032","displayName":"Serat","iconName":"Fiber_Sprite"},"amount":50}],"unlockRequirements":[{"item":{"id":"item_110001","displayName":"Cetak biru lumbung level 1","iconName":"Barn_level_1_blueprint_Sprite"},"amount":1}],"category":"None","customIcon":null,"hardnessLevel":"Basic","toolType":"None","useCategory":true,"useCustomIcon":false,"shop":{"url":"carpenter","displayName":"Carpenter"}},{"item":{"id":"item_65444","displayName":"Rumah Serangga","iconName":"Insect_house_Sprite2"},"price":10000,"daysDelay":1,"townRank":0,"tag":[],"priceOverride":7000,"priority":10,"requirements":[{"item":{"id":"item_65300","displayName":"Kompos","iconName":"Compost_Sprite"},"amount":20},{"item":{"id":"item_65063","displayName":"Kayu keras","iconName":"HardWood_Sprite"},"amount":15},{"item":{"id":"item_65108","displayName":"Getah","iconName":"Sap_Sprite"},"amount":10},{"item":{"id":"item_61006","displayName":"Batang emas","iconName":"Gold_Bar_Sprite"},"amount":1}],"unlockRequirements":[],"category":"None","customIcon":"/Game/ProjectCoral/Textures/AtlasImport/Frames/Items_Beehouse.Items_Beehouse","hardnessLevel":"Basic","toolType":"None","useCategory":true,"useCustomIcon":false,"shop":{"url":"carpenter","displayName":"Carpenter"}},{"item":{"id":"item_110008","displayName":"Gudang","iconName":"shed_icon_Sprite"},"price":20000,"daysDelay":2,"townRank":0,"tag":[],"priceOverride":0,"priority":11,"requirements":[{"item":{"id":"item_65003","displayName":"Kayu","iconName":"Wood_Sprite"},"amount":200},{"item":{"id":"item_65004","displayName":"Batu","iconName":"Stone_Sprite"},"amount":200},{"item":{"id":"item_61006","displayName":"Batang emas","iconName":"Gold_Bar_Sprite"},"amount":5}],"unlockRequirements":[],"category":"None","customIcon":null,"hardnessLevel":"Basic","toolType":"None","useCategory":true,"useCustomIcon":false,"shop":{"url":"carpenter","displayName":"Carpenter"}}],"requiredAsOffering":[{"key":"RareBased","offeringGroupTitle":"Altar Barang Langka","urlPath":"rarealtar","offeringGroupRewardText":"Membuka Akses Savannah","offerings":[{"title":"Sumber Daya Langka","imageName":"Upgrade_Resouce","numOfItemRequired":-1,"rewards":{"items":[{"item":{"id":"item_62008","displayName":"Saripati kelp osmium","iconName":"Osmium_Kelp_Essence_Sprite"},"amount":5}],"recipes":[]},"requiredItems":[{"item":{"id":"item_61006","displayName":"Batang emas","iconName":"Gold_Bar_Sprite"},"amount":3,"quality":"base"},{"item":{"id":"item_61044","displayName":"Bar perak","iconName":"Silver_Bar_Sprite"},"amount":3,"quality":"base"},{"item":{"id":"item_61005","displayName":"Batang perunggu","iconName":"Bronze_Bar_Sprite"},"amount":3,"quality":"base"},{"item":{"id":"item_62006","displayName":"Saripati kelp Emas","iconName":"Gold_Kelp_Essence_Sprite"},"amount":3,"quality":"base"},{"item":{"id":"item_62007","displayName":"Saripati kelp perak","iconName":"Silver_Kelp_Essence_Sprite"},"amount":3,"quality":"base"},{"item":{"id":"item_62005","displayName":"Saripati kelp perunggu","iconName":"Bronze_kelp_essence_Sprite"},"amount":3,"quality":"base"}]}]}]}