{
  "item": {
    "id": "item_96064",
    "displayName": "ตู้ปลาขนาดเล็ก",
    "price": 510,
    "sellPrice": 310,
    "sellAt": [],
    "stackable": true,
    "inventoryCategory": "Decoration",
    "displayKey": "Decoration",
    "description": "สำหรับตกแต่งบ้าน",
    "qualities": {},
    "iconName": "Small_aquarium_cabinet_Sprite",
    "tags": [
      "Item.Furniture.EastAsianStyle",
      "Item.Furniture.Category.Storage",
      "Item.Furniture.SubCategory.Aquarium"
    ]
  },
  "buyAt": [
    {
      "item": {
        "id": "item_96064",
        "displayName": "ตู้ปลาขนาดเล็ก",
        "iconName": "Small_aquarium_cabinet_Sprite",
        "price": 510,
        "sellPrice": 310
      },
      "allowedDays": [],
      "allowedSeasons": [],
      "allowedWeather": [],
      "forbiddenDays": [],
      "forbiddenSeasons": [],
      "forbiddenWeather": [],
      "townRank": 2,
      "tag": [],
      "priceOverride": 0,
      "priority": 0,
      "enabled": true,
      "availableSinceDate": false,
      "availableTillDate": false,
      "availableDuringTime": false,
      "shop": {
        "url": "furniture-store",
        "displayName": "Furniture Store"
      }
    }
  ]
}