[{"input":{"id":"item_50441","displayName":"Geode tanah","iconName":"Earth_geode_Sprite"},"inputAmount":1,"processingCost":20,"outputChanges":[{"item":{"id":"item_65004","displayName":"Batu","iconName":"Stone_Sprite"},"amount":10,"chance":9.68},{"item":{"id":"item_65006","displayName":"Batu bara","iconName":"Coal_Sprite"},"amount":5,"chance":9.68},{"item":{"id":"item_61001","displayName":"Bijih perunggu","iconName":"Bronze_Ore_Sprite"},"amount":5,"chance":9.68},{"item":{"id":"item_61045","displayName":"Bijih perak","iconName":"Silver_Ore_Sprite"},"amount":3,"chance":9.68},{"item":{"id":"item_61034","displayName":"Diorite","iconName":"Diorite_Sprite"},"amount":1,"chance":8.06},{"item":{"id":"item_61021","displayName":"Lepidolite","iconName":"Lepidolite_Sprite"},"amount":1,"chance":8.06},{"item":{"id":"item_61022","displayName":"Api Agate","iconName":"Fire_Agate_Sprite"},"amount":1,"chance":8.06},{"item":{"id":"item_61036","displayName":"Granit","iconName":"Granite_Sprite"},"amount":1,"chance":8.06},{"item":{"id":"item_61020","displayName":"Morganite","iconName":"Morganite_Sprite"},"amount":1,"chance":6.45},{"item":{"id":"item_61037","displayName":"Marmer","iconName":"Marble_Sprite"},"amount":1,"chance":6.45},{"item":{"id":"item_61035","displayName":"Jasper","iconName":"Jasper_Sprite"},"amount":1,"chance":4.84},{"item":{"id":"item_61041","displayName":"Kristal merah muda","iconName":"Pink_Crystal_Sprite"},"amount":1,"chance":6.45},{"item":{"id":"item_61039","displayName":"Opal hitam","iconName":"Black_Opal_Sprite"},"amount":1,"chance":3.23},{"item":{"id":"item_61040","displayName":"Beryl merah","iconName":"Red_Beryl_Sprite"},"amount":1,"chance":1.61}]},{"input":{"id":"item_50447","displayName":"Geode air","iconName":"Water_geode_Sprite"},"inputAmount":1,"processingCost":20,"outputChanges":[{"item":{"id":"item_65004","displayName":"Batu","iconName":"Stone_Sprite"},"amount":10,"chance":9.84},{"item":{"id":"item_65006","displayName":"Batu bara","iconName":"Coal_Sprite"},"amount":7,"chance":9.84},{"item":{"id":"item_61001","displayName":"Bijih perunggu","iconName":"Bronze_Ore_Sprite"},"amount":5,"chance":9.84},{"item":{"id":"item_61045","displayName":"Bijih perak","iconName":"Silver_Ore_Sprite"},"amount":5,"chance":9.84},{"item":{"id":"item_61002","displayName":"Bijih emas","iconName":"Gold_Ore_Sprite"},"amount":3,"chance":9.84},{"item":{"id":"item_61023","displayName":"Kuarsa","iconName":"Quartz_Sprite"},"amount":1,"chance":8.2},{"item":{"id":"item_61010","displayName":"Aquamarine","iconName":"Aquamarine_Sprite"},"amount":1,"chance":8.2},{"item":{"id":"item_61038","displayName":"Kristal","iconName":"Crystal_Sprite"},"amount":1,"chance":8.2},{"item":{"id":"item_61018","displayName":"Batu Bulan","iconName":"Moonstone_Sprite"},"amount":1,"chance":6.56},{"item":{"id":"item_61026","displayName":"Kuarsa biru","iconName":"blue_quartz_Sprite"},"amount":1,"chance":6.56},{"item":{"id":"item_61028","displayName":"Azurite","iconName":"Azurite_Sprite"},"amount":1,"chance":4.92},{"item":{"id":"item_61033","displayName":"Beril","iconName":"Beryl_Sprite"},"amount":1,"chance":4.92},{"item":{"id":"item_61015","displayName":"Berlian","iconName":"Diamond_Sprite"},"amount":1,"chance":3.28}]},{"input":{"id":"item_50481","displayName":"Geode angin","iconName":"Wind_geode_Sprite"},"inputAmount":1,"processingCost":20,"outputChanges":[{"item":{"id":"item_65004","displayName":"Batu","iconName":"Stone_Sprite"},"amount":15,"chance":9.68},{"item":{"id":"item_65006","displayName":"Batu bara","iconName":"Coal_Sprite"},"amount":10,"chance":9.68},{"item":{"id":"item_61001","displayName":"Bijih perunggu","iconName":"Bronze_Ore_Sprite"},"amount":5,"chance":9.68},{"item":{"id":"item_61045","displayName":"Bijih perak","iconName":"Silver_Ore_Sprite"},"amount":5,"chance":9.68},{"item":{"id":"item_61002","displayName":"Bijih emas","iconName":"Gold_Ore_Sprite"},"amount":3,"chance":9.68},{"item":{"id":"item_61012","displayName":"Kecubung","iconName":"Amethyst_Sprite"},"amount":1,"chance":8.06},{"item":{"id":"item_61027","displayName":"Visiscite","iconName":"Variscite_Sprite"},"amount":1,"chance":8.06},{"item":{"id":"item_61031","displayName":"Amber","iconName":"Amber_Sprite"},"amount":1,"chance":8.06},{"item":{"id":"item_61009","displayName":"Zamrud","iconName":"Emerald_Sprite"},"amount":1,"chance":8.06},{"item":{"id":"item_61029","displayName":"Serpentine","iconName":"Serpentine_Sprite"},"amount":1,"chance":6.45},{"item":{"id":"item_61014","displayName":"Jade","iconName":"Jade_Sprite"},"amount":1,"chance":6.45},{"item":{"id":"item_61017","displayName":"Peridot","iconName":"Peridot_Sprite"},"amount":1,"chance":4.84},{"item":{"id":"item_10002","displayName":"Berlian merah muda","iconName":"Pink_Diamond_Sprite"},"amount":1,"chance":1.61}]},{"input":{"id":"item_50446","displayName":"Geode api","iconName":"Fire_geode_Sprite"},"inputAmount":1,"processingCost":20,"outputChanges":[{"item":{"id":"item_65004","displayName":"Batu","iconName":"Stone_Sprite"},"amount":15,"chance":9.23},{"item":{"id":"item_65006","displayName":"Batu bara","iconName":"Coal_Sprite"},"amount":12,"chance":9.23},{"item":{"id":"item_61001","displayName":"Bijih perunggu","iconName":"Bronze_Ore_Sprite"},"amount":5,"chance":9.23},{"item":{"id":"item_61045","displayName":"Bijih perak","iconName":"Silver_Ore_Sprite"},"amount":5,"chance":9.23},{"item":{"id":"item_61002","displayName":"Bijih emas","iconName":"Gold_Ore_Sprite"},"amount":3,"chance":9.23},{"item":{"id":"item_61013","displayName":"Batu topas","iconName":"Topaz_Sprite"},"amount":1,"chance":7.69},{"item":{"id":"item_61019","displayName":"Onyx","iconName":"Onyx_Sprite"},"amount":1,"chance":7.69},{"item":{"id":"item_61030","displayName":"Rhodonite","iconName":"Rhodonite_Sprite"},"amount":1,"chance":7.69},{"item":{"id":"item_61025","displayName":"Rose Quartz","iconName":"Rose_Quartz_Sprite"},"amount":1,"chance":6.15},{"item":{"id":"item_61042","displayName":"Kristal ungu","iconName":"Purple_Crystal_Sprite"},"amount":1,"chance":6.15},{"item":{"id":"item_61032","displayName":"batu delima","iconName":"Garnet_Sprite"},"amount":1,"chance":6.15},{"item":{"id":"item_61016","displayName":"Opal","iconName":"Opal_Sprite"},"amount":1,"chance":4.62},{"item":{"id":"item_61024","displayName":"Labradorit","iconName":"Labradorite_Sprite"},"amount":1,"chance":4.62},{"item":{"id":"item_61011","displayName":"Rubi","iconName":"Ruby_Sprite"},"amount":1,"chance":3.08}]},{"input":{"id":"item_50474","displayName":"Geode misteri","iconName":"Mystery_geode_Sprite"},"inputAmount":1,"processingCost":20,"outputChanges":[{"item":{"id":"item_65004","displayName":"Batu","iconName":"Stone_Sprite"},"amount":10,"chance":3.49},{"item":{"id":"item_65006","displayName":"Batu bara","iconName":"Coal_Sprite"},"amount":7,"chance":3.49},{"item":{"id":"item_61001","displayName":"Bijih perunggu","iconName":"Bronze_Ore_Sprite"},"amount":5,"chance":3.49},{"item":{"id":"item_61045","displayName":"Bijih perak","iconName":"Silver_Ore_Sprite"},"amount":5,"chance":3.49},{"item":{"id":"item_61002","displayName":"Bijih emas","iconName":"Gold_Ore_Sprite"},"amount":3,"chance":3.49},{"item":{"id":"item_61004","displayName":"Bijih osmium","iconName":"Osmium_Ore_Sprite"},"amount":3,"chance":3.49},{"item":{"id":"item_61034","displayName":"Diorite","iconName":"Diorite_Sprite"},"amount":1,"chance":2.91},{"item":{"id":"item_61023","displayName":"Kuarsa","iconName":"Quartz_Sprite"},"amount":1,"chance":2.91},{"item":{"id":"item_61012","displayName":"Kecubung","iconName":"Amethyst_Sprite"},"amount":1,"chance":2.91},{"item":{"id":"item_61027","displayName":"Visiscite","iconName":"Variscite_Sprite"},"amount":1,"chance":2.91},{"item":{"id":"item_61031","displayName":"Amber","iconName":"Amber_Sprite"},"amount":1,"chance":2.91},{"item":{"id":"item_61013","displayName":"Batu topas","iconName":"Topaz_Sprite"},"amount":1,"chance":2.91},{"item":{"id":"item_61021","displayName":"Lepidolite","iconName":"Lepidolite_Sprite"},"amount":1,"chance":2.91},{"item":{"id":"item_61022","displayName":"Api Agate","iconName":"Fire_Agate_Sprite"},"amount":1,"chance":2.91},{"item":{"id":"item_61010","displayName":"Aquamarine","iconName":"Aquamarine_Sprite"},"amount":1,"chance":2.91},{"item":{"id":"item_61019","displayName":"Onyx","iconName":"Onyx_Sprite"},"amount":1,"chance":2.91},{"item":{"id":"item_61038","displayName":"Kristal","iconName":"Crystal_Sprite"},"amount":1,"chance":2.91},{"item":{"id":"item_61009","displayName":"Zamrud","iconName":"Emerald_Sprite"},"amount":1,"chance":2.91},{"item":{"id":"item_61030","displayName":"Rhodonite","iconName":"Rhodonite_Sprite"},"amount":1,"chance":2.91},{"item":{"id":"item_61036","displayName":"Granit","iconName":"Granite_Sprite"},"amount":1,"chance":2.91},{"item":{"id":"item_61020","displayName":"Morganite","iconName":"Morganite_Sprite"},"amount":1,"chance":2.33},{"item":{"id":"item_61037","displayName":"Marmer","iconName":"Marble_Sprite"},"amount":1,"chance":2.33},{"item":{"id":"item_61029","displayName":"Serpentine","iconName":"Serpentine_Sprite"},"amount":1,"chance":2.33},{"item":{"id":"item_61025","displayName":"Rose Quartz","iconName":"Rose_Quartz_Sprite"},"amount":1,"chance":2.33},{"item":{"id":"item_61042","displayName":"Kristal ungu","iconName":"Purple_Crystal_Sprite"},"amount":1,"chance":2.33},{"item":{"id":"item_61014","displayName":"Jade","iconName":"Jade_Sprite"},"amount":1,"chance":2.33},{"item":{"id":"item_61041","displayName":"Kristal merah muda","iconName":"Pink_Crystal_Sprite"},"amount":1,"chance":2.33},{"item":{"id":"item_61018","displayName":"Batu Bulan","iconName":"Moonstone_Sprite"},"amount":1,"chance":2.33},{"item":{"id":"item_61026","displayName":"Kuarsa biru","iconName":"blue_quartz_Sprite"},"amount":1,"chance":2.33},{"item":{"id":"item_61032","displayName":"batu delima","iconName":"Garnet_Sprite"},"amount":1,"chance":2.33},{"item":{"id":"item_61016","displayName":"Opal","iconName":"Opal_Sprite"},"amount":1,"chance":1.74},{"item":{"id":"item_61035","displayName":"Jasper","iconName":"Jasper_Sprite"},"amount":1,"chance":1.74},{"item":{"id":"item_61024","displayName":"Labradorit","iconName":"Labradorite_Sprite"},"amount":1,"chance":1.74},{"item":{"id":"item_61017","displayName":"Peridot","iconName":"Peridot_Sprite"},"amount":1,"chance":1.74},{"item":{"id":"item_61028","displayName":"Azurite","iconName":"Azurite_Sprite"},"amount":1,"chance":1.74},{"item":{"id":"item_61033","displayName":"Beril","iconName":"Beryl_Sprite"},"amount":1,"chance":1.74},{"item":{"id":"item_61011","displayName":"Rubi","iconName":"Ruby_Sprite"},"amount":1,"chance":1.16},{"item":{"id":"item_61039","displayName":"Opal hitam","iconName":"Black_Opal_Sprite"},"amount":1,"chance":1.16},{"item":{"id":"item_61015","displayName":"Berlian","iconName":"Diamond_Sprite"},"amount":1,"chance":1.16},{"item":{"id":"item_10002","displayName":"Berlian merah muda","iconName":"Pink_Diamond_Sprite"},"amount":1,"chance":0.58},{"item":{"id":"item_61040","displayName":"Beryl merah","iconName":"Red_Beryl_Sprite"},"amount":1,"chance":0.58}]},{"input":{"id":"item_51301","displayName":"Peti","iconName":"Coffer_Sprite"},"inputAmount":1,"processingCost":20,"outputChanges":[{"item":{"id":"item_65052","displayName":"Sampah","iconName":"Trash_Sprite"},"amount":10,"chance":5.31},{"item":{"id":"item_65202","displayName":"Kaca","iconName":"Glass_Sprite"},"amount":5,"chance":5.31},{"item":{"id":"item_62001","displayName":"Kelp Perunggu","iconName":"Bronze_kelp_Sprite"},"amount":5,"chance":5.31},{"item":{"id":"item_62003","displayName":"Kelp perak","iconName":"Silver_Kelp_Sprite"},"amount":5,"chance":5.31},{"item":{"id":"item_50408","displayName":"Hammerstone","iconName":"Hammerstone_Sprite"},"amount":1,"chance":4.42},{"item":{"id":"item_50410","displayName":"Seruit","iconName":"Harpoon_Sprite"},"amount":1,"chance":4.42},{"item":{"id":"item_50409","displayName":"Kapak tangan batu","iconName":"Stone_Hand_Axe_Sprite"},"amount":1,"chance":3.54},{"item":{"id":"item_50425","displayName":"Bel emas","iconName":"Golden_Bell_Sprite"},"amount":1,"chance":2.65},{"item":{"id":"item_50492","displayName":"Liontin Terrarium","iconName":"Terrarium_Pendant_Sprite"},"amount":1,"chance":2.65},{"item":{"id":"item_50424","displayName":"Baterai kuno","iconName":"Ancient_Battery_Sprite"},"amount":1,"chance":1.77},{"item":{"id":"item_50429","displayName":"Boneka bayangan","iconName":"Shadow_Puppet_Sprite"},"amount":1,"chance":4.42},{"item":{"id":"item_50437","displayName":"Patung tanah liat yang belum selesai","iconName":"Unfinished_Clay_Statue_Sprite"},"amount":1,"chance":4.42},{"item":{"id":"item_50482","displayName":"Cincin agate","iconName":"Gardonite_ring_Sprite"},"amount":1,"chance":4.42},{"item":{"id":"item_50484","displayName":"Locket Jade","iconName":"Jade_Locket_Sprite"},"amount":1,"chance":4.42},{"item":{"id":"item_50411","displayName":"Tombak berkarat","iconName":"Rusty_spear_Sprite"},"amount":1,"chance":3.54},{"item":{"id":"item_50417","displayName":"Mangkuk prasejarah","iconName":"Prehistoric_Bowl_Sprite"},"amount":1,"chance":3.54},{"item":{"id":"item_50427","displayName":"Perkamen Kulit","iconName":"Leather_Parchment_Sprite"},"amount":1,"chance":3.54},{"item":{"id":"item_50436","displayName":"Helm terkelupas","iconName":"Chipped_helmet_Sprite"},"amount":1,"chance":3.54},{"item":{"id":"item_50438","displayName":"Kalung manik-manik","iconName":"Beaded_Necklace_Sprite"},"amount":1,"chance":3.54},{"item":{"id":"item_50439","displayName":"Bot logam","iconName":"Metal_Boot_Sprite"},"amount":1,"chance":3.54},{"item":{"id":"item_50430","displayName":"Keris emas","iconName":"Golden_Keris_Sprite"},"amount":1,"chance":1.77},{"item":{"id":"item_50414","displayName":"Topeng Hijau","iconName":"Green_Mask_Sprite"},"amount":1,"chance":3.54},{"item":{"id":"item_50415","displayName":"Topeng Merah","iconName":"Red_Mask_Sprite"},"amount":1,"chance":3.54},{"item":{"id":"item_50416","displayName":"Topeng Biru","iconName":"Blue_Mask_Sprite"},"amount":1,"chance":3.54},{"item":{"id":"item_50420","displayName":"Palu perunggu","iconName":"Bronze_Hammer_Sprite"},"amount":1,"chance":2.65},{"item":{"id":"item_65107","displayName":"Kepingan","iconName":"Scrap_Sprite"},"amount":5,"chance":5.31}]},{"input":{"id":"item_51302","displayName":"Peti Hias","iconName":"Ornate_coffer_Sprite"},"inputAmount":1,"processingCost":20,"outputChanges":[{"item":{"id":"item_65052","displayName":"Sampah","iconName":"Trash_Sprite"},"amount":10,"chance":7.5},{"item":{"id":"item_65202","displayName":"Kaca","iconName":"Glass_Sprite"},"amount":5,"chance":7.5},{"item":{"id":"item_62001","displayName":"Kelp Perunggu","iconName":"Bronze_kelp_Sprite"},"amount":5,"chance":7.5},{"item":{"id":"item_62003","displayName":"Kelp perak","iconName":"Silver_Kelp_Sprite"},"amount":5,"chance":7.5},{"item":{"id":"item_50423","displayName":"Kapal tanah liat","iconName":"Clay_Vessel_Sprite"},"amount":1,"chance":6.25},{"item":{"id":"item_50432","displayName":"Kendi tembikar yang terkelupas","iconName":"Chipped_Pottery_Jug_Sprite"},"amount":1,"chance":6.25},{"item":{"id":"item_50433","displayName":"Kompas kuno","iconName":"Ancient_Compass_Sprite"},"amount":1,"chance":6.25},{"item":{"id":"item_50485","displayName":"Topeng Masquerade","iconName":"Masquerade_Mask_Sprite"},"amount":1,"chance":6.25},{"item":{"id":"item_50487","displayName":"Anting emas","iconName":"Gold_earring_Sprite"},"amount":1,"chance":6.25},{"item":{"id":"item_50497","displayName":"Dudukan Cincin Ukiran","iconName":"Carved_Ring_Holder_Sprite"},"amount":1,"chance":6.25},{"item":{"id":"item_50602","displayName":"Royal Bowl","iconName":"Royal_Bowl_Sprite"},"amount":1,"chance":6.25},{"item":{"id":"item_50651","displayName":"Sandal perak","iconName":"Silver_sandal_Sprite"},"amount":1,"chance":5},{"item":{"id":"item_50407","displayName":"Bola kristal salju","iconName":"Snow_Globe_Sprite"},"amount":1,"chance":3.75},{"item":{"id":"item_50412","displayName":"Tentara tanah liat","iconName":"Terracotta_Soldier_Sprite"},"amount":1,"chance":2.5},{"item":{"id":"item_50418","displayName":"Peta kuno","iconName":"Ancient_Map_Sprite"},"amount":1,"chance":2.5},{"item":{"id":"item_50426","displayName":"Prisma kaca optik","iconName":"Optical_Glass_Prism_Sprite"},"amount":1,"chance":3.75},{"item":{"id":"item_50421","displayName":"Jepit rambut ruby","iconName":"Ruby_Hairpin_Sprite"},"amount":1,"chance":1.25},{"item":{"id":"item_65107","displayName":"Kepingan","iconName":"Scrap_Sprite"},"amount":5,"chance":7.5}]},{"input":{"id":"item_51303","displayName":"Peti Berkilau","iconName":"Shimmering_coffer_Sprite"},"inputAmount":1,"processingCost":20,"outputChanges":[{"item":{"id":"item_65052","displayName":"Sampah","iconName":"Trash_Sprite"},"amount":10,"chance":7.23},{"item":{"id":"item_65202","displayName":"Kaca","iconName":"Glass_Sprite"},"amount":5,"chance":7.23},{"item":{"id":"item_62001","displayName":"Kelp Perunggu","iconName":"Bronze_kelp_Sprite"},"amount":5,"chance":7.23},{"item":{"id":"item_62003","displayName":"Kelp perak","iconName":"Silver_Kelp_Sprite"},"amount":5,"chance":7},{"item":{"id":"item_50603","displayName":"Bola Kristal Salju Pantai","iconName":"Beach_snow_globe_Sprite"},"amount":1,"chance":6.02},{"item":{"id":"item_50611","displayName":"Candlestick Batu Permata","iconName":"Gemstone_Candlestick_Sprite"},"amount":1,"chance":6.02},{"item":{"id":"item_50648","displayName":"Sundial yang rusak","iconName":"Broken_Sundial_Sprite"},"amount":1,"chance":6.02},{"item":{"id":"item_50649","displayName":"Lampu garam","iconName":"Salt_Lamp_Sprite"},"amount":1,"chance":6.02},{"item":{"id":"item_50486","displayName":"Rantai mutiara","iconName":"Pearl_Chain_Sprite"},"amount":1,"chance":4.82},{"item":{"id":"item_50404","displayName":"Patung kecil","iconName":"Small_Figurine_Sprite"},"amount":1,"chance":4.82},{"item":{"id":"item_50405","displayName":"Roda kapal","iconName":"Ships_Wheel_Sprite"},"amount":1,"chance":6.02},{"item":{"id":"item_50610","displayName":"Hourstone Hour Kaca","iconName":"Gemstone_Hourglass_Sprite"},"amount":1,"chance":4.82},{"item":{"id":"item_50612","displayName":"Lampu ajaib","iconName":"Magic_Lamp_Sprite"},"amount":1,"chance":4.82},{"item":{"id":"item_50496","displayName":"Bros mutiara","iconName":"Pearl_brooch_Sprite"},"amount":1,"chance":3.61},{"item":{"id":"item_50495","displayName":"Tongkat rambut batu giok","iconName":"Jade_Hair_Stick_Sprite"},"amount":1,"chance":3.61},{"item":{"id":"item_50605","displayName":"Teko Naga Terbang","iconName":"Flying_Dragon_Teapot_Sprite"},"amount":1,"chance":1.2},{"item":{"id":"item_50490","displayName":"Manik-manik batu permata","iconName":"Gemstone_beads_Sprite"},"amount":1,"chance":6.02},{"item":{"id":"item_65107","displayName":"Kepingan","iconName":"Scrap_Sprite"},"amount":5,"chance":7.23}]},{"input":{"id":"item_51304","displayName":"Peti Marmer","iconName":"Marble_coffer_Sprite"},"inputAmount":1,"processingCost":20,"outputChanges":[{"item":{"id":"item_65052","displayName":"Sampah","iconName":"Trash_Sprite"},"amount":10,"chance":7.06},{"item":{"id":"item_65202","displayName":"Kaca","iconName":"Glass_Sprite"},"amount":5,"chance":7.06},{"item":{"id":"item_62002","displayName":"Kelp emas","iconName":"Gold_Kelp_Sprite"},"amount":5,"chance":7.06},{"item":{"id":"item_62003","displayName":"Kelp perak","iconName":"Silver_Kelp_Sprite"},"amount":5,"chance":7.06},{"item":{"id":"item_50494","displayName":"Air mata Dragon","iconName":"Dragons_Tears_Sprite"},"amount":1,"chance":4.71},{"item":{"id":"item_50609","displayName":"Bola kristal","iconName":"Crystal_Ball_Sprite"},"amount":1,"chance":4.71},{"item":{"id":"item_50498","displayName":"Trisula Dragon","iconName":"Dragons_trisula_Sprite"},"amount":1,"chance":4.71},{"item":{"id":"item_50428","displayName":"Ukiran kayu","iconName":"Wood_Carving_Sprite"},"amount":1,"chance":3.53},{"item":{"id":"item_50422","displayName":"Piringan langit","iconName":"Sky_Disk_Sprite"},"amount":1,"chance":3.53},{"item":{"id":"item_50419","displayName":"Potret Batu","iconName":"Stone_Portrait_Sprite"},"amount":1,"chance":2.35},{"item":{"id":"item_50483","displayName":"Mahkota Jasmine","iconName":"Jasmine_Crown_Sprite"},"amount":1,"chance":5.88},{"item":{"id":"item_50488","displayName":"Gelang belang","iconName":"Shell_anklet_Sprite"},"amount":1,"chance":5.88},{"item":{"id":"item_50489","displayName":"Armband pelangi kuno","iconName":"Ancient_Rainbow_Armband_Sprite"},"amount":1,"chance":5.88},{"item":{"id":"item_50491","displayName":"Piring permata pari","iconName":"Stingray_Jewel_Plate_Sprite"},"amount":1,"chance":5.88},{"item":{"id":"item_50499","displayName":"Pisau rusak","iconName":"Broken_Blade_Sprite"},"amount":1,"chance":5.88},{"item":{"id":"item_50607","displayName":"Bonsai batu permata","iconName":"Gemstone_Bonsai_Sprite"},"amount":1,"chance":4.71},{"item":{"id":"item_50608","displayName":"Ikan emas","iconName":"Gold_fish_Sprite"},"amount":1,"chance":5.88},{"item":{"id":"item_50431","displayName":"Vas keramik","iconName":"Ceramic_Vase_Sprite"},"amount":1,"chance":1.18},{"item":{"id":"item_65107","displayName":"Kepingan","iconName":"Scrap_Sprite"},"amount":5,"chance":7.06}]},{"input":{"id":"item_51305","displayName":"Pirate Coffer","iconName":"Pirate_coffer_Sprite"},"inputAmount":1,"processingCost":20,"outputChanges":[{"item":{"id":"item_65052","displayName":"Sampah","iconName":"Trash_Sprite"},"amount":10,"chance":8.45},{"item":{"id":"item_65202","displayName":"Kaca","iconName":"Glass_Sprite"},"amount":5,"chance":8.45},{"item":{"id":"item_62002","displayName":"Kelp emas","iconName":"Gold_Kelp_Sprite"},"amount":5,"chance":8.45},{"item":{"id":"item_62003","displayName":"Kelp perak","iconName":"Silver_Kelp_Sprite"},"amount":5,"chance":8.45},{"item":{"id":"item_50650","displayName":"Bintang kaca","iconName":"Glass_Star_Sprite"},"amount":1,"chance":7.04},{"item":{"id":"item_50434","displayName":"Kipas tangan kayu","iconName":"Wooden_hand_fan_Sprite"},"amount":1,"chance":7.04},{"item":{"id":"item_50493","displayName":"Anting-anting cahaya bulan","iconName":"Moonlight_Earrings_Sprite"},"amount":1,"chance":7.04},{"item":{"id":"item_50601","displayName":"Batik Shawl","iconName":"Batik_Shawl_Sprite"},"amount":1,"chance":7.04},{"item":{"id":"item_50604","displayName":"Mangkuk kaca","iconName":"Glass_Bowl_Sprite"},"amount":1,"chance":7.04},{"item":{"id":"item_50413","displayName":"Papan bawah air","iconName":"Underwater_Tablet_Sprite"},"amount":1,"chance":5.63},{"item":{"id":"item_50406","displayName":"Jangkar berkarat","iconName":"Rusty_anchor_Sprite"},"amount":1,"chance":4.23},{"item":{"id":"item_50435","displayName":"Patung perunggu","iconName":"Bronze_Statue_Sprite"},"amount":1,"chance":2.82},{"item":{"id":"item_50403","displayName":"Sendok besar","iconName":"Oversized_Spoon_Sprite"},"amount":1,"chance":2.82},{"item":{"id":"item_50401","displayName":"Sendok perak","iconName":"Silver_Spoon_Sprite"},"amount":1,"chance":1.41},{"item":{"id":"item_50402","displayName":"Garpu perak","iconName":"Silver_Fork_Sprite"},"amount":1,"chance":1.41},{"item":{"id":"item_50606","displayName":"Model Kota","iconName":"Town_Model_Sprite"},"amount":1,"chance":4.23},{"item":{"id":"item_65107","displayName":"Kepingan","iconName":"Scrap_Sprite"},"amount":5,"chance":8.45}]},{"input":{"id":"item_51337","displayName":"Peti Misterius","iconName":"Mysterious_coffer_Sprite"},"inputAmount":1,"processingCost":20,"outputChanges":[{"item":{"id":"item_65052","displayName":"Sampah","iconName":"Trash_Sprite"},"amount":10,"chance":2.39},{"item":{"id":"item_65202","displayName":"Kaca","iconName":"Glass_Sprite"},"amount":5,"chance":2.39},{"item":{"id":"item_62001","displayName":"Kelp Perunggu","iconName":"Bronze_kelp_Sprite"},"amount":5,"chance":2.39},{"item":{"id":"item_62003","displayName":"Kelp perak","iconName":"Silver_Kelp_Sprite"},"amount":5,"chance":2.39},{"item":{"id":"item_50405","displayName":"Roda kapal","iconName":"Ships_Wheel_Sprite"},"amount":1,"chance":1.99},{"item":{"id":"item_50650","displayName":"Bintang kaca","iconName":"Glass_Star_Sprite"},"amount":1,"chance":1.99},{"item":{"id":"item_50607","displayName":"Bonsai batu permata","iconName":"Gemstone_Bonsai_Sprite"},"amount":1,"chance":1.59},{"item":{"id":"item_50609","displayName":"Bola kristal","iconName":"Crystal_Ball_Sprite"},"amount":1,"chance":1.59},{"item":{"id":"item_50610","displayName":"Hourstone Hour Kaca","iconName":"Gemstone_Hourglass_Sprite"},"amount":1,"chance":1.59},{"item":{"id":"item_50606","displayName":"Model Kota","iconName":"Town_Model_Sprite"},"amount":1,"chance":1.2},{"item":{"id":"item_50423","displayName":"Kapal tanah liat","iconName":"Clay_Vessel_Sprite"},"amount":1,"chance":1.99},{"item":{"id":"item_50432","displayName":"Kendi tembikar yang terkelupas","iconName":"Chipped_Pottery_Jug_Sprite"},"amount":1,"chance":1.99},{"item":{"id":"item_50433","displayName":"Kompas kuno","iconName":"Ancient_Compass_Sprite"},"amount":1,"chance":1.99},{"item":{"id":"item_50485","displayName":"Topeng Masquerade","iconName":"Masquerade_Mask_Sprite"},"amount":1,"chance":1.99},{"item":{"id":"item_50487","displayName":"Anting emas","iconName":"Gold_earring_Sprite"},"amount":1,"chance":1.99},{"item":{"id":"item_50497","displayName":"Dudukan Cincin Ukiran","iconName":"Carved_Ring_Holder_Sprite"},"amount":1,"chance":1.99},{"item":{"id":"item_50602","displayName":"Royal Bowl","iconName":"Royal_Bowl_Sprite"},"amount":1,"chance":1.99},{"item":{"id":"item_50651","displayName":"Sandal perak","iconName":"Silver_sandal_Sprite"},"amount":1,"chance":1.59},{"item":{"id":"item_50407","displayName":"Bola kristal salju","iconName":"Snow_Globe_Sprite"},"amount":1,"chance":1.2},{"item":{"id":"item_50412","displayName":"Tentara tanah liat","iconName":"Terracotta_Soldier_Sprite"},"amount":1,"chance":0.8},{"item":{"id":"item_50418","displayName":"Peta kuno","iconName":"Ancient_Map_Sprite"},"amount":1,"chance":0.8},{"item":{"id":"item_50426","displayName":"Prisma kaca optik","iconName":"Optical_Glass_Prism_Sprite"},"amount":1,"chance":1.2},{"item":{"id":"item_50421","displayName":"Jepit rambut ruby","iconName":"Ruby_Hairpin_Sprite"},"amount":1,"chance":0.4},{"item":{"id":"item_50603","displayName":"Bola Kristal Salju Pantai","iconName":"Beach_snow_globe_Sprite"},"amount":1,"chance":1.99},{"item":{"id":"item_50611","displayName":"Candlestick Batu Permata","iconName":"Gemstone_Candlestick_Sprite"},"amount":1,"chance":1.99},{"item":{"id":"item_50648","displayName":"Sundial yang rusak","iconName":"Broken_Sundial_Sprite"},"amount":1,"chance":1.99},{"item":{"id":"item_50649","displayName":"Lampu garam","iconName":"Salt_Lamp_Sprite"},"amount":1,"chance":1.99},{"item":{"id":"item_50486","displayName":"Rantai mutiara","iconName":"Pearl_Chain_Sprite"},"amount":1,"chance":1.59},{"item":{"id":"item_50404","displayName":"Patung kecil","iconName":"Small_Figurine_Sprite"},"amount":1,"chance":1.59},{"item":{"id":"item_50612","displayName":"Lampu ajaib","iconName":"Magic_Lamp_Sprite"},"amount":1,"chance":1.59},{"item":{"id":"item_50496","displayName":"Bros mutiara","iconName":"Pearl_brooch_Sprite"},"amount":1,"chance":1.2},{"item":{"id":"item_50495","displayName":"Tongkat rambut batu giok","iconName":"Jade_Hair_Stick_Sprite"},"amount":1,"chance":1.2},{"item":{"id":"item_50605","displayName":"Teko Naga Terbang","iconName":"Flying_Dragon_Teapot_Sprite"},"amount":1,"chance":0.4},{"item":{"id":"item_50494","displayName":"Air mata Dragon","iconName":"Dragons_Tears_Sprite"},"amount":1,"chance":1.59},{"item":{"id":"item_50498","displayName":"Trisula Dragon","iconName":"Dragons_trisula_Sprite"},"amount":1,"chance":1.59},{"item":{"id":"item_50428","displayName":"Ukiran kayu","iconName":"Wood_Carving_Sprite"},"amount":1,"chance":1.2},{"item":{"id":"item_50422","displayName":"Piringan langit","iconName":"Sky_Disk_Sprite"},"amount":1,"chance":1.2},{"item":{"id":"item_50419","displayName":"Potret Batu","iconName":"Stone_Portrait_Sprite"},"amount":1,"chance":0.8},{"item":{"id":"item_50483","displayName":"Mahkota Jasmine","iconName":"Jasmine_Crown_Sprite"},"amount":1,"chance":1.99},{"item":{"id":"item_50488","displayName":"Gelang belang","iconName":"Shell_anklet_Sprite"},"amount":1,"chance":1.99},{"item":{"id":"item_50489","displayName":"Armband pelangi kuno","iconName":"Ancient_Rainbow_Armband_Sprite"},"amount":1,"chance":1.99},{"item":{"id":"item_50491","displayName":"Piring permata pari","iconName":"Stingray_Jewel_Plate_Sprite"},"amount":1,"chance":1.99},{"item":{"id":"item_50499","displayName":"Pisau rusak","iconName":"Broken_Blade_Sprite"},"amount":1,"chance":1.99},{"item":{"id":"item_50608","displayName":"Ikan emas","iconName":"Gold_fish_Sprite"},"amount":1,"chance":1.99},{"item":{"id":"item_50431","displayName":"Vas keramik","iconName":"Ceramic_Vase_Sprite"},"amount":1,"chance":0.4},{"item":{"id":"item_50434","displayName":"Kipas tangan kayu","iconName":"Wooden_hand_fan_Sprite"},"amount":1,"chance":1.99},{"item":{"id":"item_50493","displayName":"Anting-anting cahaya bulan","iconName":"Moonlight_Earrings_Sprite"},"amount":1,"chance":1.99},{"item":{"id":"item_50601","displayName":"Batik Shawl","iconName":"Batik_Shawl_Sprite"},"amount":1,"chance":1.99},{"item":{"id":"item_50604","displayName":"Mangkuk kaca","iconName":"Glass_Bowl_Sprite"},"amount":1,"chance":1.99},{"item":{"id":"item_50413","displayName":"Papan bawah air","iconName":"Underwater_Tablet_Sprite"},"amount":1,"chance":1.59},{"item":{"id":"item_50406","displayName":"Jangkar berkarat","iconName":"Rusty_anchor_Sprite"},"amount":1,"chance":1.2},{"item":{"id":"item_50435","displayName":"Patung perunggu","iconName":"Bronze_Statue_Sprite"},"amount":1,"chance":0.8},{"item":{"id":"item_50403","displayName":"Sendok besar","iconName":"Oversized_Spoon_Sprite"},"amount":1,"chance":0.8},{"item":{"id":"item_50401","displayName":"Sendok perak","iconName":"Silver_Spoon_Sprite"},"amount":1,"chance":0.4},{"item":{"id":"item_50402","displayName":"Garpu perak","iconName":"Silver_Fork_Sprite"},"amount":1,"chance":0.4},{"item":{"id":"item_50490","displayName":"Manik-manik batu permata","iconName":"Gemstone_beads_Sprite"},"amount":1,"chance":1.99},{"item":{"id":"item_50652","displayName":"Pemain Cassete","iconName":"Cassete_Player_Sprite"},"amount":1,"chance":1.99},{"item":{"id":"item_50653","displayName":"C.I. Jo","iconName":"C_I__Jo_Sprite"},"amount":1,"chance":1.59},{"item":{"id":"item_50654","displayName":"Dumbphone","iconName":"Dumbphone_Sprite"},"amount":1,"chance":1.99},{"item":{"id":"item_50655","displayName":"Botol air","iconName":"Water_Bottle_Sprite"},"amount":1,"chance":1.59},{"item":{"id":"item_50656","displayName":"Piringan hitam","iconName":"Vinyl_record_Sprite"},"amount":1,"chance":1.59},{"item":{"id":"item_65107","displayName":"Kepingan","iconName":"Scrap_Sprite"},"amount":5,"chance":2.39}]}]