{"item":{"id":"item_41400","displayName":"Jus sea spud","price":565,"sellPrice":340,"sellAt":[],"stackable":true,"inventoryCategory":"Produk artisan","displayKey":"ArtisanProduct","description":"Sebotol jus buah yang sehat.","qualities":{"bronze":{"price":650,"sellPrice":390},"silver":{"price":735,"sellPrice":440},"gold":{"price":850,"sellPrice":510},"osmium":{"price":1135,"sellPrice":680}},"iconName":"Underwater_fruit_juice_Sprite","tags":["income.farming","Artisan.Keg","Item.Consumable.Drink","item.UnderwaterArtisan"]},"artisanResult":[{"useCategory":false,"day":0,"time":{"hours":12,"minutes":0},"additionalInput":[],"input":{"amount":1,"item":{"id":"item_21082","displayName":"Sea spud","iconName":"Sea_Spud_Sprite"}},"output":{"amount":1,"item":{"id":"item_41400","displayName":"Jus sea spud","iconName":"Underwater_fruit_juice_Sprite","sellPrice":340}},"genericInput":null,"machine":"Keg"},{"useCategory":false,"day":0,"time":{"hours":6,"minutes":0},"additionalInput":[],"input":{"amount":1,"item":{"id":"item_41400","displayName":"Jus sea spud","iconName":"Underwater_fruit_juice_Sprite"}},"output":{"amount":1,"item":{"id":"item_41400","displayName":"Jus sea spud","iconName":"Underwater_fruit_juice_Sprite","sellPrice":340}},"genericInput":null,"refinements":[{"from":"silver","to":"gold","day":0,"time":{"hours":9,"minutes":0}},{"from":"gold","to":"osmium","day":0,"time":{"hours":17,"minutes":0}}],"machine":"SlimeOfTransmutation"}],"artisanIngredient":[{"useCategory":false,"day":4,"time":{"hours":0,"minutes":0},"additionalInput":[],"input":{"amount":1,"item":{"id":"item_41400","displayName":"Jus sea spud","iconName":"Underwater_fruit_juice_Sprite"}},"output":{"amount":1,"item":{"id":"item_41385","displayName":"Wine sea spud","iconName":"Underwater_purple_wine_Sprite","sellPrice":1530}},"genericInput":null,"refinements":[{"from":"base","to":"bronze","day":3,"time":{"hours":12,"minutes":0}},{"from":"bronze","to":"silver","day":3,"time":{"hours":2,"minutes":0}},{"from":"silver","to":"gold","day":2,"time":{"hours":16,"minutes":0}},{"from":"gold","to":"osmium","day":2,"time":{"hours":0,"minutes":0}}],"machine":"Barrel"},{"useCategory":false,"day":0,"time":{"hours":6,"minutes":0},"additionalInput":[],"input":{"amount":1,"item":{"id":"item_41400","displayName":"Jus sea spud","iconName":"Underwater_fruit_juice_Sprite"}},"output":{"amount":1,"item":{"id":"item_41400","displayName":"Jus sea spud","iconName":"Underwater_fruit_juice_Sprite","sellPrice":340}},"genericInput":null,"refinements":[{"from":"silver","to":"gold","day":0,"time":{"hours":9,"minutes":0}},{"from":"gold","to":"osmium","day":0,"time":{"hours":17,"minutes":0}}],"machine":"SlimeOfTransmutation"}],"usedToCook":[{"key":"item_80088","amount":1,"cookingKey":"StoneSoup","item":{"id":"item_80088","displayName":"Sup batu","price":50,"sellPrice":5,"sellAt":[],"stackable":true,"inventoryCategory":"Consumable","displayKey":"Consumable","description":"Tidak terlihat bisa dimakan. Mengkonsumsi risiko Anda sendiri.","qualities":{"bronze":{"price":58,"sellPrice":6},"silver":{"price":63,"sellPrice":6},"gold":{"price":75,"sellPrice":8},"osmium":{"price":100,"sellPrice":10}},"iconName":"Stone_Soup_Sprite","tags":["income.other","Item.Consumable.Food"]},"craftingUnlock":{"key":"item_80088","masteryLevel":4,"masteryType":"Mining"},"utensils":["Pot"],"genericIngredients":[{"amount":1,"genericItem":{"key":"Any_Edible","tags":["Item.Consumable.Drink","Item.Consumable.Food"],"iconName":"T_AnyIngridient_Sprite","displayName":"Bahan Makanan Apapun"},"key":"Any_Edible"}],"ingredients":[{"item":{"id":"item_65004","displayName":"Batu","iconName":"Stone_Sprite"},"amount":1}],"eitherOrIngredients":[],"additionsToGenerics":{"Bahan Makanan Apapun":[{"id":"item_41180","displayName":"Yogurt kambing","iconName":"Goat_Yoghurt_Sprite"},{"id":"item_41181","displayName":"Yogurt kambing besar","iconName":"Large_Goat_Yoghurt_Sprite"}]}}],"consumables":{"base":{"key":"item_41400","bVaryHealthToMax":false,"healthDelta":190,"bVaryStaminaToMax":false,"staminaDelta":95,"level":0,"overwriteDuration":false,"duration":0,"buff":"None","itemType":"Food"},"bronze":{"key":"item_41400-a","bVaryHealthToMax":false,"healthDelta":215,"bVaryStaminaToMax":false,"staminaDelta":110,"level":0,"overwriteDuration":false,"duration":0,"buff":"None","itemType":"Food"},"silver":{"key":"item_41400-b","bVaryHealthToMax":false,"healthDelta":235,"bVaryStaminaToMax":false,"staminaDelta":120,"level":0,"overwriteDuration":false,"duration":0,"buff":"None","itemType":"Food"},"gold":{"key":"item_41400-c","bVaryHealthToMax":false,"healthDelta":280,"bVaryStaminaToMax":false,"staminaDelta":145,"level":0,"overwriteDuration":false,"duration":0,"buff":"None","itemType":"Food"},"osmium":{"key":"item_41400-d","bVaryHealthToMax":false,"healthDelta":375,"bVaryStaminaToMax":false,"staminaDelta":190,"level":0,"overwriteDuration":false,"duration":0,"buff":"None","itemType":"Food"}}}