{"item":{"id":"item_65057","displayName":"Espantapájaros monstruoso","price":10000,"sellPrice":455,"sellAt":[],"stackable":true,"inventoryCategory":"Farming","displayKey":"Farming","description":"Evita que los cuervos se acerquen a los cultivos. Protege una área de 11x11 casillas.","qualities":{},"iconName":"Monster_Scarecrow_Sprite","tags":[]},"craftedFrom":[{"key":"item_65057","displayName":"Monster scarecrow","amount":1,"ingredients":[{"item":{"id":"item_50510","displayName":"Esencia de monstruo","iconName":"Monster_Essence_Sprite"},"amount":2},{"item":{"id":"item_65107","displayName":"Chatarra","iconName":"Scrap_Sprite"},"amount":10}],"genericIngredients":[{"key":"Any_Wool","amount":1,"genericItem":{"key":"Any_Wool","tags":["item.artisan.SheepWoolCloth"],"iconName":"Wool_Cloth","displayName":"Wool Cloth","items":[{"id":"item_42011","displayName":"Tela de lana","iconName":"Wool_Cloth_Sprite"},{"id":"item_42021","displayName":"Tela de lana grande","iconName":"Large_Wool_Cloth_Sprite"}]}}],"category":"Scarecrow","item":{"id":"item_65057","displayName":"Espantapájaros monstruoso","price":10000,"sellPrice":455,"sellAt":[],"stackable":true,"inventoryCategory":"Farming","displayKey":"Farming","description":"Evita que los cuervos se acerquen a los cultivos. Protege una área de 11x11 casillas.","qualities":{},"iconName":"Monster_Scarecrow_Sprite","tags":[]}}],"buyAt":[{"item":{"id":"item_65057","displayName":"Espantapájaros monstruoso","iconName":"Monster_Scarecrow_Sprite","price":10000,"sellPrice":455},"allowedDays":[],"allowedSeasons":[],"allowedWeather":[],"forbiddenDays":[],"forbiddenSeasons":[],"forbiddenWeather":[],"townRank":0,"tag":[],"priceOverride":0,"priority":0,"enabled":true,"availableSinceDate":false,"availableTillDate":false,"availableDuringTime":false,"requirements":{"key":"slain20enemyTypes","type":"And","requirements":[{"type":"IsAchievementCompleted","meta":{"achievement":{"id":"slain20enemyTypes","title":"Intocable","description":"Mata 20 tipos de enemigos","iconName":"40_Untouchable"}}}]},"effects":[{"type":"UnlockCraftingRecipe","meta":{"item":{"id":"item_65057","displayName":"Espantapájaros monstruoso","iconName":"Monster_Scarecrow_Sprite"}}}],"shop":{"url":"concerned-monkey","displayName":"Concerned Monkey"}}]}