{
  "item": {
    "id": "item_24010-3",
    "displayName": "Muda de fruta da serpente",
    "price": 1200,
    "sellPrice": 720,
    "sellAt": [
      "Sam"
    ],
    "stackable": true,
    "inventoryCategory": "Seedling",
    "displayKey": "Seedling",
    "description": "Plante no Inverno ou na Primavera. Cresce em {cropGrowLength} dias. Requer área de 2x2 de quadrados arados. A produção pode ter qualidade prata.",
    "qualities": {},
    "iconName": "Snake_fruit_seedling_Sprite",
    "tags": [
      "income.farming"
    ]
  }
}