{
  "item": {
    "id": "item_97062",
    "displayName": "Vela de parede pequena de bruxo",
    "price": 1700,
    "sellPrice": 1020,
    "sellAt": [],
    "stackable": true,
    "inventoryCategory": "Decoration",
    "displayKey": "Decoration",
    "description": "Decoração para casa.",
    "qualities": {},
    "iconName": "Wizard_small_wall_candle_Sprite",
    "tags": [
      "Item.Furniture.WizardlyStyle",
      "Item.Furniture.Category.Electronic",
      "Item.Furniture.SubCategory.WallLamp"
    ]
  }
}