{
  "item": {
    "id": "item_96113",
    "displayName": "Pintura em pergaminho lunar",
    "price": 350,
    "sellPrice": 210,
    "sellAt": [],
    "stackable": true,
    "inventoryCategory": "Decoration",
    "displayKey": "Decoration",
    "description": "Decoração para casa.",
    "qualities": {},
    "iconName": "Lunar_Scroll_Painting_Sprite",
    "tags": [
      "Item.Furniture.EastAsianStyle",
      "Item.Furniture.Category.Wall-Mounted",
      "Item.Furniture.SubCategory.Wall Decor"
    ]
  }
}