{
  "item": {
    "id": "item_65351",
    "displayName": "Arco de sucata",
    "price": 75,
    "sellPrice": 30,
    "sellAt": [],
    "stackable": true,
    "inventoryCategory": "Decor",
    "displayKey": "Decor",
    "description": "Coloque na fazenda.",
    "qualities": {},
    "iconName": "Scrap_Arch_Sprite",
    "tags": []
  },
  "craftedFrom": [
    {
      "key": "item_65351",
      "displayName": "Scrap arch",
      "amount": 1,
      "ingredients": [
        {
          "item": {
            "id": "item_65107",
            "displayName": "Sucata",
            "iconName": "Scrap_Sprite"
          },
          "amount": 10
        }
      ],
      "genericIngredients": [],
      "category": "Decor",
      "craftingUnlock": {
        "key": "item_65351",
        "masteryLevel": 5,
        "masteryType": "Diving"
      },
      "item": {
        "id": "item_65351",
        "displayName": "Arco de sucata",
        "price": 75,
        "sellPrice": 30,
        "sellAt": [],
        "stackable": true,
        "inventoryCategory": "Decor",
        "displayKey": "Decor",
        "description": "Coloque na fazenda.",
        "qualities": {},
        "iconName": "Scrap_Arch_Sprite",
        "tags": []
      }
    }
  ]
}